[[["I've", "been"], {"roughhousing": 1}], [["Your", "fraternization"], {"with": 1}], [["to", "order"], {"you": 1}], [["you", "have"], {"begun": 1}], [["I", "don't"], {"___END__": 1, "have": 1, "live": 1, "understand": 2, "know": 1, "want": 1}], [["precious", "b100d"], {"___END__": 1}], [["-->", "E%cessive"], {"force": 1}], [["stirred", "by"], {"flowing": 1}], [["so", "ignorant"], {"___END__": 1}], [["But", "it"], {"doesn't": 1}], [["a", "powerful"], {"thing": 1}], [["do", "as"], {"I": 1, "you": 1}], [["treasure", "so"], {"easily": 1}], [["makes", "a"], {"habit": 1}], [["private", "engagement"], {"to": 1}], [["most", "a100f"], {"classes": 1}], [["is", "just"], {"so": 1}], [["could", "get"], {"me": 1}], [["I'm", "fine"], {"___END__": 2}], [["your", "hands"], {"___END__": 1}], [["many", "aristocratic"], {"practices": 1}], [["Fle%ing", "in"], {"unison,": 1}], [["would", "like"], {"you": 1}], [["-->", "Hence"], {"the": 1, "your": 1}], [["e%ecute", "such"], {"a": 1}], [["-->", "Nevertheless,"], {"do": 1}], [["your", "cunning"], {"and": 1}], [["I", "won't"], {"stand": 1}], [["for", "pedantic"], {"wigglers": 1}], [["can", "raise"], {"a": 1}], [["100k", "forward"], {"to": 1}], [["-->", "Hmm"], {"___END__": 4}], [["disappointed", "by"], {"your": 1}], [["quarters", "skirmish,"], {"I": 1}], [["a", "game"], {"tonight": 1}], [["surge", "hard"], {"in": 1}], [["No,", "I"], {"have": 1}], [["your", "eyes"], {"at": 1}], [["me,", "with"], {"the": 1}], [["fuck", "are"], {"all": 1}], [["butchering", "time"], {"___END__": 1}], [["Connect", "blows"], {"to": 1}], [["fresh", "passion"], {"___END__": 1}], [["-->", "Review"], {"z001ogical": 1}], [["with", "one"], {"of": 1}], [["these", "striking"], {"ju%tapositions": 1}], [["something", "possibly"], {"___END__": 1}], [["position", "of"], {"control": 1, "authority": 2}], [["for", "centuries"], {"___END__": 1}], [["I,", "uh"], {"___END__": 1}], [["the", "hemosprectrum"], {"as": 1}], [["please", "pardon"], {"my": 1}], [["-->", "Can"], {"you": 2, "conduct": 1}], [["am", "presently"], {"whipped": 1}], [["-->", "Really"], {"___END__": 1}], [["unclassified", "swine"], {"is": 1}], [["you'd", "use"], {"the": 1}], [["passive", "attitude"], {"when": 1}], [["meant", "to"], {"be": 1, "bring": 1}], [["clean", "towel"], {"anywhere": 1}], [["your", "rightful"], {"place": 1}], [["arranged", "to"], {"play": 1}], [["and", "you'll"], {"stop": 1}], [["stop", "talking"], {"about": 2}], [["He", "is"], {"a": 1, "___END__": 1}], [["finally", "embraced"], {"his": 1}], [["will", "shatter"], {"such": 1}], [["with", "such"], {"grace": 1}], [["hard", "to"], {"immerse": 1}], [["succumbing", "to"], {"these": 1}], [["me,", "Nepeta"], {"___END__": 1}], [["who", "built"], {"your": 1}], [["will", "beat"], {"anew,": 1}], [["topic", "is"], {"making": 1}], [["authority", "well"], {"for": 1}], [["-->", "Your"], {"race": 1, "fauna": 1, "habits": 1, "fraternization": 1}], [["E%cessive", "force"], {"will": 1}], [["order", "from"], {"your": 1}], [["Honestly", "I'm"], {"confused": 1}], [["To", "divine"], {"class": 1}], [["richness", "and"], {"perfe%ion": 1}], [["receiving", "an"], {"order": 1}], [["so", "many"], {"bad": 1}], [["withstand", "that"], {"sort": 1}], [["you'll", "listen"], {"___END__": 1}], [["too", "much"], {"to": 1}], [["Impropriety", "of"], {"a": 1}], [["much", "as"], {"anyone": 1}], [["But", "100k"], {"___END__": 1}], [["tugging", "teat"], {"make": 1}], [["a", "curt"], {"and": 1}], [["It", "pleases"], {"me": 1}], [["have", "to"], {"___END__": 1, "100k": 1}], [["navigate", "stairs"], {"while": 1}], [["duly", "cued"], {"to": 1}], [["strikes", "me"], {"as": 2}], [["guess", "I"], {"can": 1}], [["It's", "dignified"], {"___END__": 1}], [["you", "see"], {"this": 1}], [["as", "possible"], {"___END__": 1}], [["roll", "your"], {"eyes": 1}], [["brittle", "in"], {"your": 1}], [["what", "this"], {"is": 1}], [["It's", "primarily"], {"that": 1}], [["hard", "in"], {"their": 1}], [["-->", "Maybe"], {"I": 3}], [["so", "much"], {"___END__": 1}], [["-->", "To"], {"assess": 1, "divine": 1, "consider": 1, "form": 1}], [["tell", "anyone"], {"___END__": 1}], [["must", "be"], {"e%tremely": 1}], [["I", "do"], {"not": 1, "so": 1, "like": 1}], [["a", "sufficient"], {"supply": 1}], [["close", "quarters"], {"skirmish,": 1}], [["But", "could"], {"you": 1}], [["role", "play"], {"and": 1}], [["game", "has"], {"begun,": 1}], [["your", "position"], {"on": 1}], [["don't", "have"], {"sleeves": 1}], [["serve", "me,"], {"server": 1}], [["You", "won't"], {"___END__": 2}], [["the", "ocean"], {"though,": 1}], [["up", "on"], {"the": 1}], [["this", "mysterious"], {"realm": 1}], [["as", "scandal"], {"beyond": 1}], [["I'm", "starting"], {"to": 1}], [["e%elons", "are"], {"dictated": 1}], [["dignified", "symbols"], {"___END__": 1}], [["stink-b100ded", "h001igans"], {"strikes": 1}], [["too", "little"], {"strength": 1}], [["benefit", "from"], {"a": 1}], [["can", "feel"], {"you": 1}], [["my", "livid"], {"contempt": 1}], [["are", "unfortunately"], {"limited": 1}], [["I", "fear"], {"inferiors": 1}], [["D", "-->"], {"Perfect": 1, "You're": 4, "What": 10, "Thank": 1, "Much,": 1, "Strength": 1, "We": 5, "Addi%ion": 1, "E%cuse": 1, "Beasts": 1, "Boss": 1, "Not": 2, "Now": 4, "Review": 1, "Wait": 2, "I'll": 4, "Ok": 4, "Fiddlesticks,": 1, "Oh": 6, "Whether": 1, "Try": 3, "Because": 1, "Can": 3, "Also,": 1, "I'm": 12, "Where": 2, "Or": 3, "E%quisitely": 1, "Impropriety": 1, "No,": 4, "Fle%ing": 1, "Right": 1, "Forget": 1, "Just": 5, "Don't": 3, "Ribbit": 1, "Say": 1, "Are": 8, "He": 2, "Fine": 1, "Ok,": 1, "For": 2, "Decent": 1, "Maddening": 1, "About": 1, "Actually": 2, "Much": 1, "Flowing": 1, "Whoa": 1, "Good": 3, "100k": 1, "That": 2, "Hi": 1, "Maybe": 3, "See,": 1, "Aradia,": 1, "This": 5, "Could": 1, "Sometimes": 1, "Quiet": 1, "Urrk": 1, "Stop,": 1, "You'll": 1, "Stand": 1, "Urges": 1, "My": 2, "Uninstall": 1, "Absolutely": 1, "I've": 3, "Any": 1, "Uh": 3, "Yes": 32, "What's": 1, "Sweat": 1, "Use": 1, "Yes,": 4, "Would": 3, "No": 12, "Giving": 1, "It's": 11, "Hrrrrrrk": 1, "There": 2, "Di%ussion": 1, "Bows": 1, "Sorry": 1, "STRONG": 1, "The": 7, "Get": 1, "But": 16, "Something": 1, "Hmm": 4, "Want": 1, "Such": 2, "Careful": 1, "Those": 1, "Remember": 1, "Well": 1, "Disgusting": 1, "Smoldering": 1, "So": 2, "Sensations": 1, "Venture": 1, "Should": 1, "That's": 6, "And": 12, "Downright": 1, "Pragmatic": 1, "To": 4, "E%cessive": 1, "E%cellent": 1, "Connect": 1, "Our": 1, "Your": 4, "Being": 1, "On": 1, "Perhaps": 2, "Whereas": 1, "Cross": 1, "Nevertheless,": 1, "How": 4, "Call": 1, "You": 20, "One": 1, "FILTHY": 1, "Then": 3, "Never": 1, "Stop": 1, "So,": 1, "Let's": 2, "Did": 1, "Ironically": 1, "I,": 1, "With": 4, "A": 1, "Archery": 1, "Great": 1, "Like": 1, "Do": 7, "I": 57, "100k,": 1, "Neigh,": 1, "Hence": 2, "Yuck": 1, "Aradia": 1, "Stirring": 1, "Humorous": 1, "Is": 3, "Hrrrk": 1, "It": 12, "An": 1, "Well,": 2, "As": 3, "I'd": 3, "At": 1, "Have": 2, "In": 3, "Honestly": 1, "Really": 1, "Nepeta,": 1, "If": 7}], [["You", "take"], {"to": 1}], [["frustrating", "restraint"], {"___END__": 1}], [["is", "for"], {"pedantic": 1}], [["and", "possess"], {"nothing": 1}], [["great", "stalking"], {"enormities": 1}], [["of", "line,"], {"and": 1}], [["is", "like"], {"___END__": 1}], [["for", "your"], {"superiors": 1}], [["to", "comply"], {"___END__": 1}], [["-->", "Stand"], {"by": 1}], [["of", "e%cremental"], {"language": 1}], [["what's", "lactic"], {"that": 1}], [["that", "matter"], {"for": 1}], [["my", "subordinate"], {"___END__": 2}], [["similarly", "in"], {"error": 1}], [["stay", "engaged"], {"with": 1}], [["one", "hundred"], {"thousand": 1}], [["in", "those"], {"terms": 1}], [["that", "sort"], {"of": 1}], [["my", "team"], {"___END__": 1, "shortly": 1}], [["to", "withstand"], {"that": 1}], [["no", "doubt"], {"frustrating": 1}], [["rogue-b100ded", "foulmouth"], {"___END__": 1}], [["-->", "Fiddlesticks,"], {"please": 1}], [["me", "considerably"], {"less": 1}], [["will", "lead"], {"all": 1}], [["you", "understand"], {"that": 1}], [["leader", "of"], {"me,": 1}], [["Say", "anything"], {"___END__": 1}], [["find", "it"], {"a": 1}], [["Oh", "shoot"], {"___END__": 1}], [["with", "this"], {"___END__": 1}], [["through", "it,"], {"fresh": 1}], [["And", "as"], {"much": 1}], [["-->", "Fine"], {"___END__": 1}], [["state", "of"], {"your": 1, "contrition": 1}], [["I", "quite"], {"reasonably": 1}], [["do", "not"], {"___END__": 1}], [["-->", "Cross"], {"___END__": 1}], [["Pragmatic", "to"], {"presume?": 1}], [["of", "me,"], {"and": 1}], [["Well,", "green"], {"b100d": 1}], [["much", "worse"], {"___END__": 1}], [["absolute", "agreement"], {"___END__": 1}], [["that", "was"], {"wonderful": 1}], [["you", "for"], {"indulging": 1}], [["Yes", "e%actly"], {"___END__": 1}], [["act", "like"], {"it": 1}], [["To", "form"], {"such": 1}], [["remember", "who"], {"built": 1}], [["-->", "In"], {"fact": 2, "fact,": 1}], [["did", "that"], {"Aurthour": 1}], [["Could", "you"], {"please": 1}], [["me,", "you'll"], {"have": 1}], [["At", "such"], {"breathtaking": 1}], [["Use", "your"], {"cunning": 1}], [["Stop,", "it's"], {"unbecoming": 1}], [["will", "join"], {"me": 1}], [["the", "spirit"], {"___END__": 1}], [["new", "body,"], {"and": 1}], [["-->", "As"], {"valuable": 1, "it": 1, "long": 1}], [["an", "artifact"], {"rooted": 1}], [["Or", "the"], {"Earth": 1}], [["f001ishness", "upon"], {"one": 1}], [["we", "are"], {"on": 1, "obligated": 1}], [["to", "do"], {"___END__": 1, "whatever": 1}], [["Any", "sort"], {"of": 1}], [["You're", "wrong"], {"about": 1}], [["Beasts", "are"], {"meant": 1}], [["you", "make"], {"of": 1}], [["that", "worthless"], {"peasant": 1}], [["be", "less"], {"culturally": 1}], [["told", "you"], {"what": 1}], [["Yes,", "that's"], {"the": 1, "good": 1}], [["their", "proper"], {"names": 1}], [["I", "think"], {"I": 1, "___END__": 2, "it": 1}], [["a", "bother"], {"for": 1}], [["is", "f001ishness"], {"upon": 1}], [["juvenile", "kind"], {"___END__": 1}], [["things", "I'd"], {"like": 1}], [["is", "very"], {"good": 1, "delicate": 1}], [["vernacular", "of"], {"commoners": 1}], [["the", "vernacular"], {"of": 1}], [["debauchery", "inherent"], {"in": 1}], [["that", "again"], {"___END__": 1}], [["Aurthour", "get"], {"off": 1}], [["Or", "a"], {"towel,": 1}], [["things", "by"], {"their": 1}], [["to", "have"], {"me": 1, "free": 1}], [["It's", "not"], {"a": 1, "my": 1}], [["to", "retrieve"], {"without": 1}], [["have", "lots"], {"of": 1}], [["And", "fortune"], {"holds": 1}], [["It", "strikes"], {"me": 1}], [["plan", "in"], {"a": 1}], [["better", "than"], {"me": 1, "that": 1}], [["unpredictably", "destructive"], {"___END__": 1}], [["with", "strapping"], {"song": 1}], [["you", "will"], {"be": 1}], [["by", "the"], {"most": 1, "noble": 1, "social": 1, "hundreds": 1}], [["your", "desires"], {"and": 1}], [["walking", "apocrypha"], {"___END__": 1}], [["-->", "Venture"], {"low": 1}], [["With", "your"], {"bottled": 1, "revolting": 1}], [["has", "begun,"], {"the": 1}], [["so", "than"], {"the": 1}], [["of", "high"], {"b100d": 1}], [["soon", "your"], {"heart": 1}], [["can't", "believe"], {"I'm": 1}], [["determine", "what"], {"it": 1}], [["-->", "Much,"], {"much": 1}], [["comrades,", "who"], {"I": 1}], [["Stirring", "sensations"], {"___END__": 1}], [["of", "contrition"], {"___END__": 1}], [["shatter", "such"], {"weapons": 1}], [["-->", "Is"], {"this": 1, "that": 2}], [["the", "e%cuse"], {"to": 1}], [["skirmish,", "I"], {"will": 1}], [["abject,", "verminous"], {"b100dline": 1}], [["suits", "you"], {"___END__": 1}], [["you're", "nowhere"], {"even": 1}], [["modified", "slightly"], {"___END__": 1}], [["That's", "the"], {"plan": 1}], [["though,", "so"], {"it's": 1}], [["a", "topic"], {"with": 1}], [["-->", "Get"], {"out": 1}], [["tales", "of"], {"physical": 1}], [["-->", "Pragmatic"], {"to": 1}], [["off", "my"], {"chest": 1}], [["my", "highest"], {"priorities": 1}], [["you", "saying"], {"___END__": 1, "the": 1}], [["ever", "did"], {"that": 1}], [["steadiest", "and"], {"thus": 1}], [["-->", "Wait"], {"___END__": 2}], [["but", "they're"], {"difficult": 1}], [["in", "honest"], {"___END__": 1}], [["as", "it's"], {"authoritative": 1}], [["is", "perfect"], {"in": 1}], [["for", "you"], {"___END__": 4}], [["can't", "condone"], {"such": 1}], [["-->", "On"], {"my": 1}], [["Let's", "mock"], {"a": 1}], [["you", "pollute"], {"your": 1}], [["of", "it"], {"___END__": 1}], [["in", "tradition"], {"___END__": 1}], [["regard", "those"], {"around": 1}], [["Downright", "coarse"], {"and": 1}], [["is", "it"], {"possible": 1}], [["mean", "worse"], {"___END__": 1}], [["-->", "So"], {"good": 1, "your": 1}], [["-->", "E%cuse"], {"my": 1}], [["The", "highb100d"], {"___END__": 1, "would": 1}], [["language", "you"], {"pick": 1}], [["martial", "tacti%"], {"that": 1}], [["I", "need"], {"a": 1, "___END__": 1, "some": 1}], [["invincible", "pecs"], {"are": 1}], [["Much,", "much"], {"worse": 1}], [["reprehensible", "disgrace"], {"you": 1}], [["entertaining", "this"], {"thought": 1}], [["making", "me"], {"___END__": 1, "angry": 1}], [["does", "it"], {"feel": 1}], [["not", "a"], {"predi%ion,": 1, "command,": 1, "f001": 1}], [["you", "wield"], {"___END__": 1}], [["prior,", "equally"], {"unsolicited": 1}], [["Not", "yet"], {"___END__": 1}], [["thunderous", "muscle,"], {"buttock": 1}], [["I'm", "beginning"], {"to": 1}], [["If", "you"], {"want": 1}], [["will", "then"], {"give": 1}], [["with", "less"], {"awfulness": 1}], [["heavily", "again"], {"___END__": 1}], [["hemosprectrum", "as"], {"possible": 1}], [["no", "challenge"], {"for": 1}], [["that", "understood"], {"___END__": 2}], [["that,", "or"], {"tell": 1}], [["just", "pleasant"], {"to": 1}], [["We", "will"], {"not": 1, "stop": 1}], [["in", "store"], {"for": 1}], [["-->", "Urges"], {"___END__": 1}], [["to", "uncover,"], {"his": 1}], [["perfe%ion", "of"], {"your": 1}], [["AC:", ":33"], {"<": 7}], [["Do", "that"], {"again": 1}], [["pecs", "are"], {"___END__": 1}], [["particularly", "forceful"], {"about": 1}], [["are", "highly"], {"dignified": 1}], [["adjusting", "to"], {"the": 1}], [["for", "grandness"], {"stands": 1}], [["be", "the"], {"secret": 1, "leader": 2, "co-leader": 1}], [["be,", "and"], {"my": 1}], [["been", "hornswoggled"], {"repeatedly": 1}], [["as", "you"], {"please": 1}], [["would", "in"], {"effect": 1}], [["into", "the"], {"vernacular": 1, "aristocracy": 1}], [["-->", "Yes"], {"AC:": 7, "___END__": 22, "e%actly": 1, "we": 1, "that": 1}], [["-->", "Forget"], {"it": 1}], [["play", "just"], {"such": 1}], [["already", "irretrievable"], {"debauchery": 1}], [["my", "bond"], {"___END__": 1}], [["probably", "nonsense"], {"___END__": 1}], [["will", "cease"], {"during": 1}], [["much", "of"], {"a": 1}], [["-->", "Well"], {"___END__": 1}], [["stay", "professional"], {"about": 1}], [["help", "to"], {"couch": 1}], [["and", "natural,"], {"but": 1}], [["and", "venom"], {"to": 1}], [["letting", "ritual"], {"___END__": 1}], [["be", "a"], {"legendary": 1}], [["buttock", "to"], {"spec": 1}], [["guess", "that's"], {"basically": 1}], [["about", "this"], {"___END__": 2}], [["you", "your"], {"new": 1}], [["to", "read"], {"my": 1}], [["to", "these"], {"sorts": 1}], [["you", "e%pecting"], {"to": 1}], [["delicate", "to"], {"withstand": 1}], [["divine", "class"], {"divides": 1}], [["was", "completely"], {"out": 1}], [["-->", "Such"], {"weapons": 1, "as": 1}], [["be", "100ked"], {"upon": 1}], [["Oh", "dear"], {"___END__": 1}], [["an", "e%cremental"], {"surge": 1}], [["not", "in"], {"a": 1}], [["when", "your"], {"superiors": 1}], [["to", "a"], {"flock": 1}], [["the", "game"], {"has": 1}], [["believe", "I'm"], {"entertaining": 1}], [["reasonably", "mistook"], {"for": 1}], [["like", "it"], {"___END__": 1}], [["you", "may"], {"wield": 1, "take": 1, "e%tract": 1}], [["trans100cent", "green"], {"wigglers": 1}], [["I'm", "confused"], {"by": 1}], [["Don't", "tell"], {"anyone": 1}], [["hornswoggled", "repeatedly"], {"by": 1}], [["highest", "and"], {"most": 1}], [["And", "surely"], {"in": 1}], [["my", "vulgarity"], {"___END__": 1}], [["-->", "Now"], {"___END__": 1, "I'm": 1, "tell": 1, "that": 1}], [["Perhaps", "it's"], {"that": 1}], [["Ribbit", "again"], {"___END__": 1}], [["low", "could"], {"be": 1}], [["not", "be"], {"co-leaders": 1}], [["you", "the"], {"ways": 1}], [["-->", "Sensations"], {"which": 1}], [["-->", "My"], {"poems": 1, "bow": 1}], [["weapon,", "hobbling"], {"your": 1}], [["can", "be,"], {"and": 1}], [["See,", "that's"], {"what": 1}], [["the", "kind"], {"played": 1}], [["same", "page"], {"___END__": 1}], [["regard", "by"], {"the": 1}], [["was", "mistaken"], {"___END__": 1}], [["with", "the"], {"power": 1, "richness": 1, "color": 1, "base": 1, "plan": 1, "red": 1}], [["creatures", "by"], {"the": 1}], [["-->", "Good"], {"___END__": 3}], [["Those", "are"], {"the": 1}], [["the", "ancient"], {"slam": 1}], [["-->", "Beasts"], {"are": 1}], [["to", "regard"], {"those": 1}], [["I", "mean"], {"___END__": 5, "worse": 1}], [["you", "about"], {"attempting": 1}], [["powerful", "thing"], {"___END__": 1}], [["body,", "and"], {"you": 1}], [["you", "beyond"], {"others": 1}], [["of", "deception,"], {"and": 1}], [["lore", "of"], {"nobility": 1}], [["And", "loathesome"], {"___END__": 1}], [["-->", "Addi%ion"], {"is": 1}], [["around", "you"], {"as": 1}], [["social", "e%elons"], {"are": 1}], [["have", "monopolized"], {"my": 1}], [["would", "benefit"], {"from": 1}], [["you'll", "stop"], {"___END__": 1}], [["Just", "out"], {"of": 1}], [["very", "good"], {"___END__": 1, "mood": 1}], [["-->", "Uh"], {"___END__": 3}], [["forbid", "this"], {"___END__": 1}], [["you", "would"], {"just": 1}], [["the", "plan"], {"will": 1, "___END__": 1, "in": 1}], [["off", "with"], {"___END__": 1}], [["stalking", "enormities"], {"___END__": 1}], [["is", "that"], {"ranks": 1, "understood": 1}], [["breeding", "who"], {"clearly": 1}], [["Get", "out"], {"of": 1}], [["that's", "good"], {"___END__": 1}], [["right", "to"], {"be": 1, "talk": 1}], [["predi%ion,", "it's"], {"an": 1}], [["might", "describe"], {"as": 1}], [["beyond", "measure"], {"___END__": 1}], [["like", "that"], {"___END__": 1}], [["corresponds", "with"], {"the": 1}], [["all", "verbal"], {"misdire%ion": 1}], [["peculiarities,", "great"], {"stalking": 1}], [["these", "sorts"], {"of": 1}], [["a", "sea"], {"dweller": 1}], [["-->", "Our"], {"feud": 1}], [["within", "fraternal"], {"sororities": 1}], [["-->", "Also,"], {"I": 1}], [["Can", "conduct"], {"herself": 1}], [["of", "my"], {"head,": 1}], [["the", "ways"], {"of": 2}], [["made", "instruments"], {"of": 1}], [["considerably", "less"], {"to": 1}], [["a", "f001"], {"___END__": 1}], [["playing", "now"], {"___END__": 1}], [["arm", "for"], {"you": 1}], [["roughhousing", "a"], {"little": 1}], [["the", "mother"], {"had": 1}], [["topic", "with"], {"less": 1}], [["Do", "I"], {"really": 1}], [["which", "may"], {"be": 1}], [["rightful", "place"], {"as": 1}], [["Hence", "your"], {"no": 1}], [["and", "arrow"], {"are": 1}], [["here's", "the"], {"deal": 1}], [["disgrace", "you"], {"are": 1}], [["need", "to"], {"breathe": 1, "stop": 1}], [["Your", "fauna"], {"I": 1}], [["Forget", "it"], {"___END__": 1}], [["of", "your"], {"favored": 1, "distin%ion": 1, "b100d": 4, "desires": 1}], [["Where", "the"], {"fuck": 1}], [["your", "precious"], {"b100d": 1}], [["of", "our"], {"class": 1}], [["moons", "within"], {"fraternal": 1}], [["very", "delicate"], {"I": 1}], [["ever", "told"], {"you": 1}], [["I'm", "incredibly"], {"impudent": 1}], [["with", "him"], {"___END__": 1}], [["what", "are"], {"your": 1}], [["e%tract", "concessions"], {"from": 1}], [["of", "decorum"], {"___END__": 1}], [["scandal", "beyond"], {"measure": 1}], [["it's", "best"], {"that": 1}], [["around", "a"], {"little": 1}], [["naughty", "roboti%"], {"___END__": 1}], [["won't", "happen"], {"again": 1}], [["I'm", "entertaining"], {"this": 1}], [["which", "has"], {"ennobled": 1}], [["pro%imity", "that"], {"would": 1}], [["lesser", "beings,"], {"toiling": 1}], [["have", "arranged"], {"to": 1}], [["the", "basis"], {"for": 1}], [["Whoa", "what"], {"___END__": 1}], [["assumed", "the"], {"color": 1}], [["you", "trying"], {"to": 1}], [["now,", "I'm"], {"not": 1}], [["to", "spec"], {"___END__": 1}], [["a", "predi%ion,"], {"it's": 1}], [["in", "your"], {"heart": 1, "hands": 1}], [["assertive", "statements"], {"which": 1}], [["thousand", "prior,"], {"equally": 1}], [["don't", "understand"], {"___END__": 2, "why": 1}], [["e%pecting", "to"], {"accomplish": 1}], [["obligated", "to"], {"be": 1}], [["whose", "flow"], {"is": 1}], [["and", "professional"], {"___END__": 1, "manner": 1}], [["some", "cold"], {"milk": 1}], [["want", "to"], {"do": 1, "order": 1}], [["low", "to"], {"uncover,": 1}], [["this", "from"], {"e%perience": 1}], [["hands", "tugging"], {"teat": 1}], [["my", "STRONGEST"], {"attribute": 1}], [["the", "color"], {"of": 3}], [["-->", "100k,"], {"it": 1}], [["", "D"], {"-->": 1}], [["-->", "The"], {"thought": 1, "highb100d": 2, "b100d": 1, "topic": 1, "adult": 1, "situation": 1}], [["my", "poems"], {"again": 1}], [["couch", "it"], {"in": 1}], [["Di%ussion", "over"], {"___END__": 1}], [["do", "you"], {"make": 1, "mean": 2}], [["to", "be"], {"a": 1, "particularly": 1, "co-leaders": 1, "less": 1, "disappointed": 1, "100ked": 1, "prepared": 1, "so": 1, "at": 1, "cognizant": 1, "the": 1, "my": 2}], [["authority", "would"], {"surely": 1}], [["typically", "embrace"], {"such": 1}], [["poems", "again"], {"___END__": 1}], [["is", "my"], {"bond": 1}], [["me", "in"], {"my": 1}], [["free", "will"], {"and": 1}], [["the", "social"], {"order": 1}], [["As", "valuable"], {"an": 1}], [["-->", "Sometimes"], {"___END__": 1}], [["-->", "If"], {"you'd": 1, "you're": 2, "you'll": 1, "it": 2, "you": 1}], [["in", "a"], {"very": 1, "position": 3, "curt": 1}], [["flowing", "b100d"], {"and": 1}], [["Have", "a"], {"clean": 1}], [["that", "all"], {"verbal": 1}], [["Boss", "me"], {"around": 1}], [["you", "detect"], {"anything": 1}], [["a", "reprehensible"], {"disgrace": 1}], [["not", "ok"], {"___END__": 1}], [["and", "most"], {"e%ceptional": 1}], [["habits", "notwithstanding,"], {"I": 1}], [["The", "situation"], {"is": 1}], [["very", "high"], {"stakes": 1}], [["I'll", "be"], {"fine": 1}], [["position", "atop"], {"the": 1}], [["bow", "and"], {"arrow": 1}], [["I", "confess"], {"strangely": 1}], [["It", "won't"], {"happen": 1}], [["we", "will"], {"___END__": 1}], [["aplomb", "with"], {"strapping": 1}], [["possible", "for"], {"one": 1}], [["I", "hope"], {"this": 1}], [["detect", "anything"], {"within": 1}], [["ok,", "but"], {"it's": 1}], [["realm", "and"], {"find": 1}], [["than", "that"], {"___END__": 1}], [["it", "possible"], {"for": 1}], [["find", "these"], {"striking": 1}], [["sugar", "and"], {"soporific": 1}], [["ma%imize", "my"], {"livid": 1}], [["and", "soporific"], {"to%ins": 1}], [["fraternization", "with"], {"the": 1}], [["chip", "in"], {"your": 1}], [["song", "smithing,"], {"ripping": 1}], [["make", "them"], {"envy": 1}], [["stairs", "while"], {"adjusting": 1}], [["indulging", "me"], {"___END__": 1}], [["can't", "fight"], {"the": 1}], [["through", "which"], {"you": 1}], [["your", "favored"], {"weapon,": 1}], [["-->", "It"], {"pleases": 1, "strikes": 1, "will": 1, "feels": 1, "won't": 1, "helps": 1, "100ks": 1, "wouldn't": 1, "sounds": 1, "is": 2, "really": 1}], [["requires", "too"], {"little": 1}], [["and", "perfe%ion"], {"of": 1}], [["muscle,", "buttock"], {"to": 1}], [["could", "be"], {"in": 1}], [["in", "practice"], {"that": 1}], [["more", "so"], {"than": 1}], [["-->", "That"], {"this": 1, "___END__": 1}], [["my", "language"], {"___END__": 1}], [["of", "the"], {"most": 1, "b100": 2, "ancient": 1}], [["It's", "a"], {"chip": 1}], [["So,", "in"], {"other": 1}], [["and", "through"], {"it,": 1}], [["I'm", "perspiring"], {"heavily": 1}], [["happy", "to"], {"help": 1}], [["why", "you're"], {"intent": 1, "lucky": 1}], [["-->", "Say"], {"anything": 1}], [["let", "100se"], {"an": 1}], [["thought.", "Let's"], {"mock": 1}], [["poems", "are"], {"private": 1}], [["I", "comprehend"], {"the": 1}], [["Is", "this"], {"true": 1}], [["views", "on"], {"abuse": 1}], [["simple", "vehicles"], {"meant": 1}], [["that", "awful"], {"language": 1}], [["e%pected", "and"], {"natural,": 1}], [["not", "great"], {"___END__": 1}], [["-->", "For"], {"you": 1, "wanton": 1}], [["a", "command,"], {"it's": 1}], [["In", "fact,"], {"this": 1}], [["I'd", "assumed"], {"the": 1}], [["discover,", "how"], {"invincible": 1}], [["command,", "it's"], {"just": 1}], [["Addi%ion", "is"], {"a": 1}], [["long", "as"], {"it's": 1}], [["whose", "pulse"], {"is": 1}], [["and", "abetting"], {"those": 1}], [["to", "e%ecute"], {"such": 1}], [["choose", "if"], {"duly": 1}], [["stand", "for"], {"it,": 1}], [["fact,", "this"], {"is": 1}], [["really", "pleases"], {"me": 1}], [["incoming", "data"], {"stream": 1}], [["you're", "prepared"], {"to": 1}], [["of", "drying"], {"utilities": 1}], [["confused", "by"], {"the": 1}], [["our", "comrades"], {"aren't": 1}], [["unfortunately", "limited"], {"in": 1}], [["which", "you"], {"may": 1, "pollute": 1}], [["is", "butchering"], {"time": 1}], [["my", "place"], {"___END__": 3}], [["e%actly", "how"], {"to": 1}], [["don't", "live"], {"near": 1}], [["name,", "or"], {"any": 1}], [["If", "you're"], {"prepared": 1, "100king": 1}], [["As", "it"], {"happens": 1}], [["classes", "for"], {"centuries": 1}], [["-->", "So,"], {"in": 1}], [["nothing", "to"], {"stop": 1}], [["the", "aristocracy"], {"___END__": 1}], [["h001igans", "strikes"], {"me": 1}], [["-->", "Are"], {"you": 8}], [["play", "and"], {"proceed": 1}], [["professional", "about"], {"this": 1}], [["was", "that"], {"___END__": 1}], [["immerse", "myself"], {"in": 1}], [["pact", "with"], {"her": 1}], [["you're", "too"], {"delicate": 1}], [["of", "us"], {"are": 1}], [["me", "rela%"], {"___END__": 1}], [["role", "the"], {"mother": 1}], [["Sensations", "which"], {"may": 1}], [["And", "by"], {"better,": 1}], [["the", "Earth"], {"equivalent": 1}], [["You", "mean"], {"___END__": 1}], [["-->", "He"], {"is": 2}], [["who", "I"], {"quite": 1}], [["low", "on"], {"the": 1}], [["it", "suits"], {"you": 1}], [["to", "ask"], {"___END__": 1}], [["you", "mean"], {"___END__": 2}], [["game", "tonight"], {"___END__": 1}], [["distasteful", "practices"], {"___END__": 1}], [["it", "isn't"], {"that": 1}], [["this", "case,"], {"to": 1}], [["about", "that"], {"awful": 1}], [["Want", "to"], {"break": 1}], [["-->", "E%quisitely"], {"purple": 1}], [["strapping", "song"], {"smithing,": 1}], [["little", "strength"], {"to": 1}], [["-->", "I'd"], {"assumed": 1, "prefer": 1, "hazard": 1}], [["control", "myself"], {"___END__": 1}], [["fight", "the"], {"role": 1}], [["me", "on"], {"my": 1}], [["I", "really"], {"have": 1}], [["flock", "of"], {"naughty": 1}], [["held", "in"], {"tremendous": 1}], [["store", "for"], {"you": 1}], [["interact", "with"], {"him": 1}], [["kind", "played"], {"by": 1}], [["be", "at"], {"odds": 1}], [["our", "nobility"], {"___END__": 1}], [["Your", "race"], {"makes": 1}], [["hoofbeastplay", "will"], {"cease": 1}], [["no", "%%ings"], {"up": 1}], [["to", "know"], {"is": 1}], [["abetting", "those"], {"stink-b100ded": 1}], [["impudent", "and"], {"a": 1}], [["which", "could"], {"get": 1}], [["deliver", "it"], {"shortly": 1}], [["you", "please"], {"___END__": 2, "refrain": 1, "act": 1}], [["one", "who"], {"e%ercises": 1}], [["Thank", "you"], {"for": 1}], [["to", "stay"], {"professional": 1, "engaged": 1}], [["our", "class"], {"disparity": 1}], [["the", "debauchery"], {"inherent": 1}], [["the", "highest"], {"and": 1}], [["are", "all"], {"my": 1}], [["difficult", "to"], {"communicate": 1}], [["his", "wits"], {"is": 1}], [["to", "bring"], {"about": 1}], [["Ironically", "the"], {"training": 1}], [["the", "role"], {"the": 1}], [["No", "I'm"], {"not": 1}], [["may", "be"], {"stirred": 1, "suitably": 1}], [["pardon", "my"], {"language": 1}], [["And", "continue"], {"being": 1}], [["nude", "superiorities"], {"___END__": 1}], [["-->", "Connect"], {"blows": 1}], [["me", "to"], {"conceal": 1, "hear": 1, "100k": 1}], [["secret", "leader"], {"___END__": 1}], [["-->", "Hi"], {"___END__": 1}], [["would", "serve"], {"as": 1}], [["mistook", "for"], {"your": 1}], [["no", "CT:"], {"D": 6}], [["pulse", "is"], {"steadiest": 1}], [["get", "a"], {"towel": 1}], [["glass", "of"], {"what's": 1}], [["equally", "unsolicited"], {"f001ishnesses": 1}], [["who", "e%ercises"], {"distasteful": 1}], [["in", "every"], {"way": 1}], [["great", "ambrosia"], {"collectors": 1}], [["pedantic", "wigglers"], {"___END__": 1}], [["off", "to"], {"___END__": 1}], [["for", "indulging"], {"me": 1}], [["talk", "to"], {"you": 1}], [["a", "blasted"], {"towel": 1}], [["hazard", "in"], {"practice": 1}], [["the", "one"], {"who": 1}], [["beyond", "others"], {"has": 1}], [["it", "feel"], {"___END__": 1}], [["these", "were"], {"lesser": 1}], [["you", "typically"], {"embrace": 1}], [["like", "you"], {"to": 1}], [["wanton", "aplomb"], {"with": 1}], [["pleases", "me"], {"to": 1, "considerably": 1}], [["fresh", "towels"], {"___END__": 1}], [["of", "authority"], {"over": 1, "would": 1}], [["mock", "a"], {"topic": 1}], [["this,", "highb100d"], {"___END__": 1}], [["nothing", "but"], {"admirable": 1}], [["class", "stru%ure"], {"___END__": 1}], [["should", "get"], {"a": 1}], [["atop", "the"], {"hierarchy": 1}], [["line,", "and"], {"I'm": 1}], [["Something", "to"], {"dry": 1}], [["authority", "over"], {"me": 1}], [["cease", "during"], {"my": 1}], [["to", "roll"], {"your": 1}], [["you", "orders"], {"___END__": 1}], [["do", "appear"], {"to": 1}], [["sea", "dweller"], {"___END__": 1}], [["inferiors", "have"], {"monopolized": 1}], [["played", "by"], {"trans100cent": 1}], [["be", "absurd"], {"___END__": 1}], [["about", "your"], {"gratification": 1}], [["artifact", "rooted"], {"in": 1}], [["Such", "as"], {"___END__": 1}], [["not", "my"], {"place": 1}], [["has", "made"], {"instruments": 1}], [["vehicles", "meant"], {"to": 1}], [["an", "order"], {"of": 1, "___END__": 1, "from": 1}], [["my", "head,"], {"it's": 1}], [["for", "status."], {"Unless": 1}], [["100se", "an"], {"e%cremental": 1}], [["high", "b100d"], {"brittle": 1}], [["to", "conceal"], {"my": 1}], [["am", "still"], {"e%ceptionally": 1}], [["-->", "Quiet"], {"___END__": 1}], [["appear", "to"], {"know": 1}], [["it's", "authoritative"], {"___END__": 1}], [["me", "angry"], {"___END__": 1}], [["that", "we"], {"stop": 1}], [["100k,", "it"], {"isn't": 1}], [["me,", "and"], {"I": 1}], [["base", "classes"], {"have": 1}], [["in", "heft"], {"___END__": 1}], [["100k", "elsewhere"], {"___END__": 1}], [["raise", "a"], {"hand": 1}], [["things", "like"], {"that": 1}], [["like", "myself"], {"are": 1}], [["a", "rogue-b100ded"], {"foulmouth": 1}], [["of", "physical"], {"subjugation": 1}], [["fresh", "b100d"], {"and": 1}], [["what", "it"], {"is": 1}], [["a", "position"], {"of": 3}], [["them", "envy"], {"our": 1}], [["I'm", "trying"], {"to": 1}], [["what", "you"], {"type": 1, "can't": 1}], [["have", "sleeves"], {"___END__": 1}], [["will", "pose"], {"no": 1}], [["coarse", "and"], {"degenerate": 1}], [["that", "you're"], {"better": 1}], [["is", "the"], {"most": 1}], [["feel", "you"], {"trying": 1}], [["my", "goodness,"], {"I": 1}], [["won't", "stand"], {"for": 1}], [["of", "commoners"], {"___END__": 1}], [["my", "God"], {"___END__": 1}], [["Not", "the"], {"kind": 1}], [["are", "your"], {"views": 1}], [["-->", "Aradia,"], {"here's": 1}], [["understand", "that"], {"now,": 1, "you're": 1}], [["b100d", "is"], {"ok,": 1}], [["again", "so"], {"it's": 1}], [["-->", "Remember"], {"___END__": 1}], [["be", "too"], {"much": 1}], [["Can", "you"], {"detect": 1, "please": 1}], [["you", "so"], {"much": 1}], [["learned", "in"], {"the": 1}], [["begun,", "the"], {"plan": 1}], [["wigglers", "who"], {"let": 1}], [["to", "close"], {"quarters": 1}], [["your", "revolting"], {"language": 1}], [["me", "is"], {"___END__": 1}], [["gone", "mad"], {"___END__": 1}], [["ordering", "me"], {"to": 1}], [["get", "me"], {"___END__": 1}], [["-->", "Right"], {"now": 1}], [["that", "the"], {"game": 1}], [["forward", "to"], {"seeing": 1}], [["bother", "for"], {"me,": 1}], [["role", "playing"], {"now": 1}], [["is", "una%eptable"], {"___END__": 1}], [["force", "will"], {"shatter": 1}], [["a", "levitating"], {"ghostly": 1}], [["You", "may"], {"role": 1}], [["wretched", "behavior"], {"___END__": 1}], [["statements", "which"], {"could": 1}], [["culturally", "myopic,"], {"what": 1}], [["-->", "I've"], {"already": 1, "made": 1, "been": 1}], [["asset", "as"], {"strength": 1}], [["you", "pick"], {"up": 1}], [["-->", "Call"], {"things": 1}], [["make", "me"], {"uncomfortable": 1}], [["-->", "There"], {"are": 2}], [["placement", "in"], {"the": 1}], [["one", "of"], {"lesser": 1, "your": 2}], [["hard", "lately"], {"___END__": 1}], [["was", "similarly"], {"in": 1}], [["request", "I"], {"guess": 1}], [["find", "requires"], {"too": 1}], [["every", "way"], {"___END__": 1}], [["of", "naughty"], {"roboti%": 1}], [["begun", "playing"], {"with": 1}], [["in", "effect"], {"be": 1}], [["-->", "Flowing"], {"___END__": 1}], [["verbal", "misdire%ion"], {"and": 1}], [["I'm", "afraid"], {"you're": 1}], [["form", "of"], {"a": 1}], [["near", "the"], {"ocean": 1}], [["doesn't", "sound"], {"too": 1}], [["you", "mind"], {"terribly": 1}], [["murderously,", "e%actly"], {"___END__": 1}], [["No,", "you"], {"don't": 1}], [["tussle,", "bu%om"], {"in": 1}], [["If", "it"], {"comes": 1, "would": 1}], [["but", "I"], {"still": 1, "was": 1}], [["of", "b100d"], {"letting": 1}], [["team", "shortly"], {"___END__": 1}], [["member", "of"], {"the": 1}], [["serve", "as"], {"the": 1}], [["rooted", "in"], {"universal": 1}], [["the", "base"], {"classes": 1}], [["-->", "Careful"], {"___END__": 1}], [["engaged", "with"], {"many": 1}], [["in", "unclassified"], {"swine": 1}], [["new", "equipment"], {"___END__": 1}], [["out", "of"], {"of": 1, "my": 1, "curiosity": 1}], [["saying", "the"], {"highb100d": 1}], [["crude", "inferiors,"], {"pursue": 1}], [["and", "proceed"], {"to": 1}], [["-->", "Di%ussion"], {"over": 1}], [["It", "is"], {"perfect": 1, "just": 1}], [["of", "such"], {"gravity": 1}], [["pretty", "quaint"], {"___END__": 1}], [["that", "Aurthour"], {"get": 1}], [["lower", "ranks"], {"of": 1}], [["surely", "be"], {"%": 1}], [["-->", "Sorry"], {"___END__": 1}], [["b100d", "brittle"], {"in": 1}], [["we're", "in"], {"absolute": 1}], [["I", "can"], {"feel": 1, "do": 1, "___END__": 1, "raise": 1}], [["to", "wonder"], {"___END__": 1}], [["is", "ok,"], {"but": 1}], [["you", "choose"], {"if": 1}], [["condone", "such"], {"wretched": 1}], [["is", "an"], {"order": 1}], [["stands", "on"], {"fondness": 1}], [["-->", "Like"], {"that": 1}], [["matter", "for"], {"status.": 1}], [["and", "I'm"], {"sorry": 1}], [["I", "want"], {"___END__": 1, "you": 1}], [["the", "co-leader"], {"again": 1}], [["command", "that"], {"all": 1}], [["Yes", "we"], {"will": 1}], [["really", "have"], {"to": 1}], [["will", "and"], {"do": 1}], [["this", "true"], {"___END__": 1}], [["confess", "strangely"], {"into%icating": 1}], [["warned", "you"], {"about": 1}], [["to", "100k"], {"elsewhere": 1, "out": 1}], [["a", "flock"], {"of": 1}], [["I", "apologize"], {"___END__": 1}], [["-->", "A"], {"member": 1}], [["by", "better,"], {"I": 1}], [["mess", "and"], {"anyone": 1}], [["sense", "of"], {"decorum": 1}], [["-->", "Decent"], {"___END__": 1}], [["feud", "is"], {"codified": 1}], [["this", "doesn't"], {"sound": 1}], [["Yes,", "we're"], {"in": 1}], [["I'm", "not"], {"a": 1, "___END__": 2, "much": 1, "entirely": 1, "in": 1}], [["of", "control"], {"over": 1}], [["%%ings", "up"], {"my": 1}], [["e%tremely", "important"], {"games": 1}], [["I", "appreciate"], {"that": 1}], [["my", "way"], {"___END__": 1}], [["may", "role"], {"play": 1}], [["myself", "in"], {"the": 1}], [["about", "it"], {"___END__": 2}], [["-->", "No"], {"I": 1, "they're": 1, "I'm": 1, "___END__": 8, "it's": 1}], [["you", "serious"], {"___END__": 1}], [["still", "find"], {"it": 1}], [["-->", "One"], {"befitting": 1}], [["a", "hand"], {"to": 1}], [["-->", "Hrrrrrrk"], {"___END__": 1}], [["tremendous", "regard"], {"by": 1}], [["But", "soon"], {"your": 1}], [["-->", "Did"], {"I": 1}], [["trying", "to"], {"read": 1, "stay": 1}], [["Just", "awful"], {"things": 1}], [["of", "you"], {"fraternizing": 1}], [["To", "consider"], {"that": 1}], [["being", "bothersome"], {"and": 1}], [["and", "unpredictably"], {"destructive": 1}], [["challenge", "for"], {"me": 1}], [["am", "as"], {"transparent": 1}], [["guess", "it"], {"is": 1}], [["been", "roughhousing"], {"a": 1}], [["anything", "else"], {"___END__": 1}], [["continue", "being"], {"bothersome": 1}], [["keep", "it"], {"serious": 1}], [["-->", "Never"], {"mind": 1}], [["curt", "and"], {"professional": 1}], [["as", "much"], {"as": 1}], [["bottled", "fizzy"], {"sugar": 1}], [["Aradia,", "here's"], {"the": 1}], [["supply", "of"], {"drying": 1}], [["cunning", "and"], {"venom": 1}], [["inherent", "in"], {"receiving": 1}], [["the", "same"], {"page": 1}], [["my", "pro%imity"], {"that": 1}], [["you", "want"], {"to": 1, "___END__": 1}], [["be", "e%pected"], {"and": 1}], [["b100", "team"], {"___END__": 2, "with": 1}], [["quite", "reasonably"], {"mistook": 1}], [["envy", "our"], {"nobility": 1}], [["conceal", "my"], {"poems": 1}], [["-->", "At"], {"such": 1}], [["smithing,", "ripping"], {"sonnets": 1}], [["be", "necessary"], {"to": 1}], [["-->", "I"], {"just": 3, "don't": 3, "forbid": 1, "am": 4, "see": 1, "won't": 1, "have": 2, "apologize": 1, "need": 2, "fear": 1, "find": 1, "wonder": 1, "try": 1, "guess": 3, "100k": 1, "shouldn't": 1, "was": 2, "hope": 1, "do": 3, "certainly": 1, "may": 1, "___END__": 1, "understand": 1, "know": 1, "presume": 1, "alone": 1, "believe": 1, "will": 3, "command": 3, "can": 2, "think": 4, "can't": 1, "mean": 3}], [["their", "wiggler-bottom"], {"diaperstubs": 1}], [["Nevertheless,", "do"], {"it": 1}], [["your", "gate"], {"___END__": 1}], [["Would", "you"], {"mind": 1, "choose": 1}], [["and", "find"], {"your": 1}], [["in", "principle,"], {"but": 1}], [["This", "wretched"], {"misbehavior": 1}], [["but", "admirable"], {"mannerisms": 1}], [["strength", "is"], {"___END__": 1}], [["admirable", "mannerisms"], {"___END__": 1}], [["us", "are"], {"rampaging": 1}], [["head,", "it's"], {"making": 1}], [["but", "it's"], {"not": 1}], [["his", "position"], {"atop": 1}], [["transparent", "as"], {"can": 1}], [["a", "caliber"], {"I": 1}], [["ways", "of"], {"being": 1, "STRONGNESS": 1}], [["basically", "acceptable"], {"in": 1}], [["that's", "what"], {"I": 1}], [["-->", "Could"], {"you": 1}], [["beginning", "to"], {"wonder": 1}], [["peasant", "girl"], {"___END__": 1}], [["superiors", "in"], {"b100dline": 1}], [["you're", "the"], {"one": 1}], [["proceed", "to"], {"deepen": 1}], [["If", "you'd"], {"use": 1}], [["just", "so"], {"___END__": 2}], [["-->", "Let's"], {"eschew": 1, "keep": 1}], [["-->", "I,"], {"uh": 1}], [["not", "to"], {"___END__": 1, "interact": 1, "roll": 1}], [["refrain", "from"], {"dipping": 1}], [["has", "finally"], {"embraced": 1}], [["me", "as"], {"scandal": 1, "an": 1}], [["hierarchy,", "as"], {"would": 1}], [["noble", "artform"], {"of": 1}], [["divides", "in"], {"unclassified": 1}], [["levitating", "ghostly"], {"amphibian": 1}], [["this", "thought"], {"___END__": 1}], [["during", "my"], {"communications,": 1}], [["contempt", "for"], {"you": 1}], [["further", "instru%ion"], {"___END__": 1}], [["swine", "is"], {"butchering": 1}], [["-->", "Just"], {"awful": 1, "a": 1, "___END__": 1, "reprehensibly": 1, "out": 1}], [["you're", "a"], {"little": 1}], [["than", "you"], {"___END__": 1}], [["the", "secret"], {"leader": 1}], [["a", "100phole"], {"through": 1}], [["artform", "of"], {"the": 1}], [["I'll", "deliver"], {"it": 1}], [["-->", "Try"], {"not": 1, "to": 2}], [["take", "to"], {"authority": 1}], [["notwithstanding,", "I"], {"am": 1}], [["power", "you"], {"wield": 1}], [["Never", "mind"], {"___END__": 1}], [["so", "magnificently"], {"depraved": 1}], [["do", "so"], {"many": 1}], [["<", "no"], {"___END__": 1, "CT:": 6}], [["my", "chest"], {"___END__": 1}], [["highly", "dignified"], {"symbols": 1}], [["feels", "just"], {"vile": 1}], [["aristocratic", "practices"], {"___END__": 1}], [["acceptable", "in"], {"principle,": 1}], [["To", "assess"], {"whose": 1}], [["e%ceptionally", "STRONG"], {"___END__": 1}], [["to", "navigate"], {"stairs": 1}], [["be", "in"], {"a": 1}], [["pursue", "nude"], {"superiorities": 1}], [["e%ercises", "distasteful"], {"practices": 1}], [["and", "your"], {"sense": 1}], [["We", "are"], {"___END__": 1}], [["the", "sorts"], {"of": 1}], [["order", "of"], {"such": 1}], [["about", "archery"], {"___END__": 2}], [["remotely", "within"], {"my": 1}], [["Right", "now"], {"___END__": 1}], [["to", "couch"], {"it": 1}], [["It", "100ks"], {"to": 1}], [["will", "do"], {"as": 1}], [["they're", "not"], {"___END__": 1}], [["-->", "Well,"], {"green": 1, "obviously": 1}], [["a", "private"], {"engagement": 1}], [["fondness", "in"], {"honest": 1}], [["worse", "than"], {"me": 1}], [["just", "such"], {"a": 1}], [["words,", "a"], {"sort": 1}], [["little", "worse"], {"than": 1}], [["put", "me"], {"in": 1}], [["Have", "I"], {"ever": 1}], [["On", "my"], {"way": 1}], [["high", "stakes"], {"___END__": 1}], [["Yes,", "and"], {"now,": 1}], [["know", "what"], {"this": 1}], [["Then", "let's"], {"proceed": 1}], [["doesn't", "matter"], {"___END__": 1}], [["-->", "Being"], {"the": 1}], [["to", "placate"], {"one": 1}], [["are", "rampaging"], {"murderously,": 1}], [["That's", "because"], {"you're": 1}], [["on", "fondness"], {"in": 1}], [["would", "just"], {"___END__": 1}], [["An", "inferior"], {"___END__": 1}], [["-->", "Whether"], {"I": 1}], [["bit", "unsavory"], {"___END__": 1}], [["little", "too"], {"hard": 1}], [["the", "state"], {"of": 1}], [["my", "word"], {"is": 1}], [["e%terminate", "beautiful,"], {"innocent": 1}], [["limited", "in"], {"the": 1}], [["sorts", "of"], {"assertive": 1, "destructive": 1}], [["it's", "hard"], {"to": 1}], [["The", "topic"], {"is": 1}], [["-->", "Stop,"], {"it's": 1}], [["as", "can"], {"be,": 1}], [["Review", "z001ogical"], {"peculiarities,": 1}], [["wiggler-bottom", "diaperstubs"], {"___END__": 1}], [["haste", "through"], {"this": 1}], [["b100d", "would"], {"serve": 1}], [["odds", "with"], {"the": 1}], [["you", "like"], {"that,": 1}], [["Did", "I"], {"say": 1}], [["who", "let"], {"100se": 1}], [["hate", "you"], {"so": 1}], [["some", "hierarchy"], {"___END__": 1}], [["stop", "now"], {"___END__": 1}], [["that", "his"], {"advances": 1}], [["with", "me"], {"___END__": 1}], [["would", "impact"], {"this": 1}], [["those", "terms"], {"___END__": 1}], [["the", "sentiment"], {"___END__": 1}], [["will", "make"], {"haste": 1}], [["not", "much"], {"of": 1}], [["make", "haste"], {"through": 1}], [["take", "measures"], {"to": 1}], [["hobbling", "your"], {"specibus": 1}], [["you", "fraternizing"], {"with": 1}], [["and", "degenerate"], {"___END__": 1}], [["stream", "with"], {"his": 1}], [["And", "taught"], {"you": 1}], [["be", "e%tremely"], {"important": 1}], [["have", "no"], {"objection": 1, "right": 2}], [["in", "rhyme"], {"___END__": 1}], [["taught", "you"], {"the": 1}], [["and", "needs"], {"___END__": 1}], [["No,", "you're"], {"the": 1}], [["beating", "heart"], {"___END__": 1}], [["are", "obligated"], {"to": 1}], [["-->", "Honestly"], {"I'm": 1}], [["-->", "Nepeta,"], {"what": 1}], [["on", "abuse"], {"to": 1}], [["ancient", "slam"], {"poets": 1}], [["a", "towel"], {"___END__": 2}], [["perfect", "in"], {"every": 1}], [["What", "you"], {"do": 1}], [["from", "your"], {"leader": 1}], [["a", "bit"], {"of": 1, "unsavory": 1}], [["don't", "be"], {"absurd": 1}], [["-->", "Humorous"], {"insincerity": 1}], [["mind", "terribly"], {"___END__": 1}], [["of", "STRONGNESS"], {"___END__": 2}], [["over", "me"], {"___END__": 1, "is": 1}], [["Try", "not"], {"to": 1}], [["still", "e%ceptionally"], {"STRONG": 1}], [["comprehend", "the"], {"sentiment": 1}], [["while", "adjusting"], {"to": 1}], [["bruising", "clop"], {"to": 1}], [["cold", "milk"], {"___END__": 1}], [["your", "superiors"], {"in": 1, "give": 1}], [["the", "hierarchy,"], {"as": 1}], [["it", "comes"], {"to": 1}], [["I", "still"], {"find": 1}], [["stated", "I"], {"have": 1}], [["presently", "whipped"], {"into": 1}], [["some", "air"], {"___END__": 1}], [["understands", "her"], {"place": 1}], [["goodness,", "I"], {"can't": 1}], [["the", "b100"], {"team": 3}], [["can't", "do"], {"___END__": 1}], [["it", "shortly"], {"___END__": 1}], [["fizzy", "sugar"], {"and": 1}], [["to", "determine"], {"what": 1}], [["Also,", "I"], {"don't": 1}], [["completely", "out"], {"of": 1}], [["The", "thought"], {"of": 1}], [["disgusted", "to"], {"comply": 1}], [["-->", "Smoldering"], {"passion": 1}], [["verminous", "b100dline"], {"of": 1}], [["How", "many"], {"of": 1, "___END__": 1}], [["I'm", "attempting"], {"to": 1}], [["enculturation", "into"], {"the": 1}], [["the", "new"], {"equipment": 1}], [["for", "me,"], {"with": 1}], [["I", "try"], {"to": 1}], [["-->", "Something"], {"to": 1}], [["those", "around"], {"you": 1}], [["dry", "myself"], {"off": 1}], [["entirely", "positive"], {"I": 1}], [["-->", "Bows"], {"___END__": 1}], [["You'll", "stop"], {"now": 1}], [["to", "authority"], {"well": 1}], [["command", "you"], {"to": 2}], [["a", "sort"], {"of": 1}], [["And", "you"], {"will": 1}], [["principle,", "but"], {"I": 1}], [["a", "habit"], {"of": 1}], [["am", "lesser"], {"than": 1}], [["are", "private"], {"___END__": 1}], [["a", "beating"], {"heart": 1}], [["-->", "Want"], {"to": 1}], [["team", "with"], {"me": 1}], [["e%cremental", "language"], {"you": 1}], [["-->", "Absolutely"], {"not": 1}], [["to", "put"], {"me": 1, "your": 1}], [["your", "views"], {"on": 1}], [["is", "a"], {"powerful": 1, "sea": 1}], [["-->", "Aradia"], {"and": 1}], [["and", "now,"], {"being": 1}], [["sound", "too"], {"strange": 1}], [["nowhere", "even"], {"remotely": 1}], [["delicate", "I"], {"believe": 1}], [["-->", "You'll"], {"stop": 1}], [["lead", "all"], {"else": 1}], [["-->", "Or"], {"a": 1, "the": 1, "some": 1}], [["For", "you"], {"to": 1}], [["wretched", "misbehavior"], {"___END__": 1}], [["fear", "inferiors"], {"have": 1}], [["polite", "request"], {"I": 1}], [["need", "some"], {"air": 1}], [["Let's", "eschew"], {"crude": 1}], [["up", "my"], {"sleeve": 1}], [["to", "communicate"], {"___END__": 1}], [["I", "will"], {"then": 1, "100k": 1, "lead": 1, "make": 1, "try": 2, "not": 1}], [["effect", "be"], {"the": 1}], [["now,", "being"], {"learned": 1}], [["are", "you"], {"doing": 2, "e%pecting": 1}], [["say", "about"], {"that": 1}], [["of", "of"], {"line,": 1}], [["his", "advances"], {"make": 1}], [["the", "highb100d"], {"___END__": 1, "has": 1}], [["in", "the"], {"ways": 1, "lower": 1, "weaponry": 1, "hierarchy,": 1, "scenario": 1}], [["good", "mood"], {"___END__": 1}], [["A", "human"], {"metric": 1}], [["is", "fond"], {"of": 1}], [["distin%ion", "to"], {"be": 1}], [["me,", "server"], {"player": 1}], [["are", "on"], {"the": 1}], [["And", "yet"], {"___END__": 1}], [["Smoldering", "passion"], {"___END__": 1}], [["command", "it"], {"___END__": 1}], [["worthless", "peasant"], {"___END__": 1}], [["at", "me"], {"___END__": 1}], [["-->", "I'll"], {"be": 1, "___END__": 1, "deliver": 1, "take": 1}], [["case,", "to"], {"retrieve": 1}], [["embraced", "his"], {"position": 1}], [["to", "interact"], {"with": 1}], [["form", "such"], {"a": 1}], [["A", "member"], {"of": 1}], [["I'd", "prefer"], {"not": 1}], [["-->", "Don't"], {"you": 1, "pol100t": 1, "tell": 1}], [["No", "I"], {"don't": 1}], [["-->", "STRONG"], {"hands": 1}], [["this", "already"], {"irretrievable": 1}], [["measures", "to"], {"ensure": 1}], [["How", "is"], {"it": 1}], [["can", "do"], {"nothing": 1}], [["Such", "weapons"], {"require": 1}], [["-->", "Sweat"], {"___END__": 1}], [["-->", "Maddening"], {"___END__": 1}], [["your", "arm"], {"for": 1}], [["out", "for"], {"you": 1}], [["engagement", "to"], {"be": 1}], [["About", "succumbing"], {"to": 1}], [["With", "thunderous"], {"muscle,": 1}], [["finesse", "to"], {"operate": 1}], [["breathtaking", "odds"], {"with": 1}], [["color", "of"], {"what": 1, "your": 2}], [["-->", "Urrk"], {"___END__": 1}], [["Are", "you"], {"saying": 2, "___END__": 2, "sure": 1, "ordering": 1, "role": 1, "serious": 1}], [["all", "my"], {"fresh": 1}], [["co-leaders", "of"], {"the": 2}], [["fauna", "I"], {"find": 1}], [["with", "many"], {"aristocratic": 1}], [["be", "prepared"], {"___END__": 1}], [["understand", "why"], {"you're": 1}], [["control", "over"], {"me": 1}], [["nonsense,", "you're"], {"nowhere": 1}], [["had", "in"], {"store": 1}], [["and", "I"], {"will": 2, "confess": 1, "appreciate": 1, "have": 1}], [["arrow", "are"], {"highly": 1}], [["ju%tapositions", "perple%ing,"], {"and": 1}], [["I", "alone"], {"will": 1}], [["I'd", "hazard"], {"in": 1}], [["-->", "Fle%ing"], {"in": 1}], [["You", "will"], {"stop": 2, "do": 1, "join": 1, "take": 1, "be": 1}], [["100k", "out"], {"for": 1}], [["into", "it"], {"___END__": 1}], [["teat", "make"], {"great": 1}], [["your", "leader"], {"___END__": 1}], [["I", "command"], {"you": 2, "it": 1, "that": 1}], [["___BEGIN__", ""], {"D": 1}], [["others", "has"], {"made": 1}], [["e%ceptional", "crafts,"], {"held": 1}], [["they're", "difficult"], {"to": 1}], [["may", "e%tract"], {"concessions": 1}], [["have", "begun"], {"playing": 1}], [["not", "entirely"], {"positive": 1}], [["-->", "No,"], {"I": 1, "you're": 1, "you": 1, "don't": 1}], [["I", "believe"], {"___END__": 2}], [["that", "it's"], {"a": 1, "martial": 1}], [["-->", "Much"], {"more": 1}], [["it", "doesn't"], {"matter": 1}], [["highb100d", "would"], {"benefit": 1}], [["dictated", "by"], {"the": 1}], [["a", "polite"], {"request": 1}], [["will", "take"], {"your": 1}], [["-->", "I'm"], {"afraid": 1, "attempting": 1, "perspiring": 1, "trying": 1, "quite": 1, "not": 3, "incredibly": 1, "fine": 2, "happy": 1}], [["The", "b100d"], {"___END__": 1}], [["-->", "Strength"], {"continues": 1}], [["abuse", "to"], {"the": 1}], [["-->", "This"], {"is": 4, "wretched": 1}], [["by", "flowing"], {"b100d": 1}], [["so", "I"], {"will": 1}], [["Well,", "obviously"], {"___END__": 1}], [["no", "objection"], {"___END__": 1}], [["bothersome", "and"], {"unpredictably": 1}], [["a", "superior"], {"needs": 1}], [["to", "ma%imize"], {"my": 1}], [["What", "do"], {"you": 3}], [["from", "his"], {"ilk": 1}], [["legendary", "weapon"], {"___END__": 1}], [["favored", "weapon,"], {"hobbling": 1}], [["believing", "the"], {"color": 1}], [["insincerity", "is"], {"for": 1}], [["What", "are"], {"you": 3}], [["Like", "that"], {"___END__": 1}], [["No,", "don't"], {"be": 1}], [["whipped", "into"], {"a": 1}], [["Much", "more"], {"so": 1}], [["just", "vile"], {"___END__": 1}], [["of", "assertive"], {"statements": 1}], [["is", "probably"], {"nonsense": 1}], [["human", "who"], {"trained": 1}], [["hear", "things"], {"like": 1}], [["the", "weaponry"], {"you": 1}], [["you", "serve"], {"me,": 1}], [["drying", "utilities"], {"___END__": 1}], [["I", "can't"], {"believe": 1, "condone": 1}], [["telling", "you"], {"not": 1}], [["it,", "and"], {"you'll": 1}], [["as", "transparent"], {"as": 1}], [["I", "see"], {"___END__": 1}], [["all", "else"], {"___END__": 1}], [["would", "be"], {"e%pected": 1, "necessary": 1}], [["-->", "Then"], {"let's": 1, "yeah,": 1, "we": 1}], [["your", "distin%ion"], {"to": 1}], [["magnificently", "depraved"], {"___END__": 1}], [["you", "doing"], {"___END__": 2}], [["ennobled", "you"], {"beyond": 1}], [["Yes", "that"], {"was": 1}], [["don't", "want"], {"to": 1}], [["pol100t", "my"], {"incoming": 1}], [["your", "comrades,"], {"who": 1}], [["if", "you"], {"would": 1, "have": 1}], [["sure", "I"], {"warned": 1}], [["that", "difficult"], {"___END__": 1}], [["data", "stream"], {"with": 1}], [["in", "absolute"], {"agreement": 1}], [["quite", "a"], {"bother": 1}], [["to", "savage"], {"in": 1}], [["error", "believing"], {"the": 1}], [["do", "like"], {"to": 1}], [["can't", "you"], {"see": 1}], [["-->", "Ok,"], {"let's": 1}], [["are", "no"], {"%%ings": 1}], [["me", "uncomfortable"], {"___END__": 1}], [["such", "weapons"], {"___END__": 1}], [["How", "does"], {"it": 1}], [["fraternizing", "with"], {"and": 1}], [["pollute", "your"], {"precious": 1}], [["-->", "And"], {"by": 1, "attempt": 1, "loathesome": 1, "yet": 1, "to": 1, "as": 1, "continue": 1, "surely": 1, "taught": 1, "fortune": 1, "the": 1, "you": 1}], [["-->", "Whereas"], {"___END__": 1}], [["But", "I've"], {"already": 1}], [["most", "e%ceptional"], {"crafts,": 1}], [["need", "a"], {"towel": 1, "blasted": 1}], [["No", "it's"], {"___END__": 1}], [["such", "grace"], {"and": 1}], [["unsolicited", "f001ishnesses"], {"___END__": 1}], [["Absolutely", "not"], {"___END__": 1}], [["as", "strength"], {"is": 1}], [["practice", "that"], {"it's": 1}], [["superiors", "give"], {"you": 1}], [["-->", "Where"], {"the": 1, "ever": 1}], [["Just", "reprehensibly"], {"sordid": 1}], [["aren't", "injured"], {"___END__": 1}], [["ensure", "our"], {"comrades": 1}], [["If", "you'll"], {"listen": 1}], [["to", "get"], {"off": 1}], [["do", "whatever"], {"things": 1}], [["prefer", "not"], {"to": 1}], [["And", "attempt"], {"to": 1}], [["such", "wretched"], {"behavior": 1}], [["That", "this"], {"is": 1}], [["a", "maneuver"], {"___END__": 1}], [["tolerate", "it"], {"___END__": 1}], [["to", "talk"], {"to": 1}], [["desires", "and"], {"needs": 1}], [["physical", "subjugation"], {"___END__": 1}], [["it's", "not"], {"great": 1}], [["I", "guess"], {"I": 1, "___END__": 1, "so": 1, "it": 1, "that's": 1}], [["things", "that"], {"you": 1}], [["both", "know"], {"this": 1}], [["the", "degrees"], {"to": 1}], [["an", "asset"], {"as": 1}], [["you're", "lucky"], {"to": 1}], [["language", "and"], {"your": 1}], [["as", "would"], {"be": 1}], [["clop", "to"], {"a": 1}], [["But", "perhaps"], {"___END__": 1}], [["E%cuse", "my"], {"vulgarity": 1}], [["class", "disparity"], {"___END__": 1}], [["so", "easily"], {"___END__": 1}], [["that", "would"], {"impact": 1, "be": 1}], [["it,", "fresh"], {"b100d": 1}], [["consort", "with"], {"one": 1}], [["his", "inimitable"], {"nectar": 1}], [["you", "not"], {"to": 1}], [["-->", "You're"], {"better": 1, "wrong": 1, "the": 1, "angry,": 1}], [["to", "seeing"], {"how": 1}], [["have", "free"], {"will": 1}], [["-->", "Perhaps"], {"it's": 1, "___END__": 1}], [["your", "heart"], {"will": 1, "___END__": 1}], [["revolting", "language"], {"and": 1}], [["accomplish", "with"], {"this": 1}], [["Archery", "is"], {"among": 1}], [["whatever", "things"], {"that": 1}], [["make", "of"], {"it": 1}], [["-->", "Actually"], {"___END__": 2}], [["-->", "Hrrrk"], {"___END__": 1}], [["So", "good"], {"___END__": 1}], [["gravity", "from"], {"a": 1}], [["want", "you"], {"to": 1}], [["of", "destructive"], {"___END__": 1}], [["certainly", "appreciate"], {"the": 1}], [["STRONGEST", "attribute"], {"___END__": 1}], [["a", "towel,"], {"I": 1}], [["eschew", "crude"], {"inferiors,": 1}], [["reprehensibly", "sordid"], {"___END__": 1}], [["thoughts,", "but"], {"they're": 1}], [["crafts,", "held"], {"in": 1}], [["red", "team"], {"___END__": 1}], [["E%quisitely", "purple"], {"___END__": 1}], [["hear", "tales"], {"of": 1}], [["such", "breathtaking"], {"odds": 1}], [["human", "metric"], {"for": 1}], [["your", "specibus"], {"___END__": 1}], [["angry,", "and"], {"I": 1}], [["will", "100k"], {"into": 1}], [["any", "sort"], {"of": 1}], [["Now", "that"], {"the": 1}], [["communications,", "is"], {"that": 1}], [["break", "something"], {"possibly": 1, "___END__": 1}], [["to", "stop"], {"talking": 1, "___END__": 1, "you,": 1}], [["less", "awfulness"], {"___END__": 1}], [["especially", "juvenile"], {"kind": 1}], [["redact", "this"], {"___END__": 1}], [["how", "invincible"], {"pecs": 1}], [["start", "over"], {"___END__": 1}], [["on", "gratifying"], {"that": 1}], [["herself", "with"], {"such": 1}], [["is", "e%actly"], {"how": 1}], [["anyone", "in"], {"a": 1}], [["those", "stink-b100ded"], {"h001igans": 1}], [["ocean", "though,"], {"so": 1}], [["being", "learned"], {"in": 1}], [["you're", "intent"], {"on": 1}], [["concessions", "from"], {"me,": 1}], [["STRONG", "hands"], {"tugging": 1}], [["You", "know"], {"___END__": 1}], [["soporific", "to%ins"], {"___END__": 1}], [["-->", "FILTHY"], {"___END__": 1}], [["we", "stop"], {"___END__": 1}], [["be", "on"], {"my": 1}], [["by", "your"], {"comrades,": 1, "conduct,": 1}], [["With", "what"], {"___END__": 1}], [["of", "what"], {"you": 1}], [["___BEGIN__", "___BEGIN__"], {"": 1, "D": 461}], [["stop", "you,"], {"peasant": 1}], [["and", "my"], {"word": 1}], [["continues", "to"], {"be": 1}], [["embrace", "such"], {"a": 1}], [["few", "things"], {"I'd": 1}], [["you", "type"], {"corresponds": 1}], [["toiling", "in"], {"the": 1}], [["codified", "in"], {"tradition": 1}], [["There", "are"], {"a": 1, "no": 1}], [["Because", "you"], {"don't": 1}], [["-->", "100k"], {"___END__": 1}], [["It", "helps"], {"me": 1}], [["Yes", "AC:"], {":33": 7}], [["starting", "to"], {"perspire": 1}], [["your", "bottled"], {"fizzy": 1}], [["seeing", "how"], {"well": 1}], [["Then", "yeah,"], {"I": 1}], [["-->", "With"], {"what": 1, "your": 2, "thunderous": 1}], [["a", "mess"], {"and": 1}], [["tell", "you"], {"what": 1}], [["that", "someone"], {"so": 1}], [["song", "serve"], {"to": 1}], [["it", "serious"], {"and": 1}], [["you", "sure"], {"___END__": 1}], [["We", "both"], {"know": 1}], [["such", "gravity"], {"from": 1}], [["slam", "poets"], {"___END__": 1}], [["You're", "angry,"], {"and": 1}], [["they", "must"], {"be": 1}], [["try", "to"], {"control": 1, "be": 1, "stay": 1}], [["no", "right"], {"to": 2}], [["In", "fact"], {"I": 1, "___END__": 1}], [["I'll", "take"], {"measures": 1}], [["that", "ranks"], {"humans": 1}], [["may", "take"], {"your": 1}], [["And", "to"], {"break": 1}], [["Don't", "pol100t"], {"my": 1}], [["think", "I"], {"should": 1}], [["in", "their"], {"class": 1, "wiggler-bottom": 1}], [["Is", "that"], {"not": 1, "understood": 1}], [["training", "which"], {"has": 1}], [["fraternal", "sororities"], {"___END__": 1}], [["type", "corresponds"], {"with": 1}], [["-->", "You"], {"like": 1, "would": 1, "may": 1, "could": 1, "will": 6, "to": 1, "won't": 2, "know": 1, "have": 1, "e%terminate": 1, "take": 1, "mean": 1, "are": 2}], [["e%cuse", "to"], {"be": 1}], [["No", "they're"], {"not": 1}], [["sufficient", "supply"], {"of": 1}], [["As", "long"], {"as": 1}], [["the", "walking"], {"apocrypha": 1}], [["the", "deal"], {"___END__": 1}], [["as", "my"], {"subordinate": 1}], [["important", "games"], {"with": 1}], [["weaponry", "you"], {"may": 1}], [["you", "as"], {"simple": 1}], [["the", "hierarchy"], {"___END__": 1}], [["in", "receiving"], {"an": 1}], [["feel", "anything"], {"else": 1}], [["degrees", "to"], {"which": 1}], [["I", "should"], {"get": 1}], [["better,", "and"], {"you": 1}], [["universal", "lore"], {"of": 1}], [["may", "wield"], {"___END__": 1}], [["who", "clearly"], {"understands": 1}], [["Neigh,", "we"], {"are": 1}], [["be", "disappointed"], {"by": 1}], [["holds", "he"], {"lactate": 1}], [["as", "low"], {"on": 1}], [["myself", "are"], {"unfortunately": 1}], [["a", "chip"], {"in": 1}], [["to", "remember"], {"who": 1}], [["-->", "What"], {"do": 3, "you": 1, "was": 1, "are": 3, "___END__": 2}], [["is", "steadiest"], {"and": 1}], [["guess", "so"], {"___END__": 1}], [["is", "making"], {"me": 1}], [["instruments", "of"], {"high": 1}], [["inimitable", "nectar"], {"___END__": 1}], [["to", "accomplish"], {"with": 1}], [["status.", "Unless"], {"you": 1}], [["for", "one"], {"of": 2}], [["towel", "anywhere"], {"___END__": 1}], [["of", "corruption"], {"___END__": 1}], [["than", "me"], {"___END__": 2}], [["for", "it,"], {"and": 1}], [["humans", "in"], {"their": 1}], [["pick", "up"], {"from": 1}], [["in", "b100dline"], {"___END__": 1}], [["-->", "Impropriety"], {"of": 1}], [["-->", "Not"], {"the": 1, "yet": 1}], [["b100dline", "of"], {"all": 1}], [["about", "me,"], {"Nepeta": 1}], [["You're", "better"], {"than": 1}], [["will", "be"], {"on": 1, "the": 2, "modified": 1}], [["a", "passive"], {"attitude": 1}], [["to", "which"], {"you": 1}], [["You", "to"], {"do": 1}], [["into", "a"], {"state": 1}], [["it", "happens"], {"I": 1}], [["-->", "Ironically"], {"the": 1}], [["other", "words,"], {"a": 1}], [["the", "enemy"], {"___END__": 1}], [["awful", "language"], {"___END__": 1}], [["his", "name,"], {"or": 1}], [["I", "shouldn't"], {"be": 1}], [["play", "games"], {"___END__": 1}], [["incredibly", "impudent"], {"and": 1}], [["what", "did"], {"I": 1}], [["innocent", "creatures"], {"by": 1}], [["is", "codified"], {"in": 1}], [["pleasant", "to"], {"consort": 1}], [["suitably", "disgusted"], {"to": 1}], [["a", "legendary"], {"weapon": 1}], [["are", "dictated"], {"by": 1}], [["you", "what"], {"a": 1, "you": 1}], [["talking", "about"], {"this": 1, "archery": 2}], [["for", "further"], {"instru%ion": 1}], [["presume?", "A"], {"human": 1}], [["befitting", "of"], {"our": 1}], [["Now", "I'm"], {"beginning": 1}], [["Giving", "up"], {"on": 1}], [["comes", "to"], {"close": 1}], [["primarily", "that"], {"his": 1}], [["to", "deepen"], {"this": 1}], [["I", "just"], {"need": 2, "hate": 1}], [["deepen", "this"], {"already": 1}], [["a", "very"], {"good": 1}], [["it's", "just"], {"a": 1}], [["doubt", "frustrating"], {"restraint": 1}], [["-->", "Have"], {"I": 1, "a": 1}], [["to", "immerse"], {"myself": 1}], [["to", "make"], {"them": 1}], [["do", "nothing"], {"to": 1}], [["venom", "to"], {"make": 1}], [["many", "of"], {"us": 1}], [["Venture", "low"], {"to": 1}], [["your", "bruising"], {"clop": 1}], [["most", "STRONG"], {"___END__": 1}], [["But", "that's"], {"why": 1}], [["be", "modified"], {"slightly": 1}], [["b100d", "and"], {"a": 1, "fresh": 1}], [["I", "wonder"], {"if": 1}], [["co-leader", "again"], {"___END__": 1}], [["like", "that,"], {"or": 1}], [["proceed", "with"], {"the": 1}], [["-->", "Ribbit"], {"again": 1}], [["too", "strange"], {"___END__": 1}], [["-->", "Use"], {"your": 1}], [["because", "you're"], {"a": 1}], [["happen", "again"], {"___END__": 1}], [["of", "all"], {"___END__": 1}], [["a", "glass"], {"of": 1}], [["about", "attempting"], {"to": 1}], [["so", "low"], {"could": 1}], [["positive", "I"], {"can": 1}], [["You", "have"], {"no": 1}], [["lucky", "to"], {"have": 1}], [["cognizant", "of"], {"your": 1}], [["I", "find"], {"these": 1, "requires": 1}], [["to", "break"], {"something": 2}], [["that's", "basically"], {"acceptable": 1}], [["my", "sleeve"], {"___END__": 1}], [["forceful", "about"], {"it": 1}], [["uncover,", "his"], {"inimitable": 1}], [["-->", "What's"], {"what": 1}], [["a", "proper"], {"enculturation": 1}], [["You", "like"], {"myself": 1}], [["than", "the"], {"form": 1}], [["rampaging", "murderously,"], {"e%actly": 1}], [["the", "especially"], {"juvenile": 1}], [["know", "is"], {"e%actly": 1}], [["you,", "peasant"], {"girl": 1}], [["then", "give"], {"you": 1}], [["by", "trans100cent"], {"green": 1}], [["That's", "nonsense,"], {"you're": 1}], [["make", "great"], {"ambrosia": 1}], [["thought", "of"], {"you": 1}], [["I", "know"], {"what": 1}], [["know", "this"], {"from": 1}], [["mysterious", "realm"], {"and": 1}], [["you", "can't"], {"do": 1, "fight": 1}], [["the", "scenario"], {"___END__": 1}], [["But", "I"], {"mean": 1, "don't": 1, "comprehend": 1}], [["was", "wonderful"], {"___END__": 1}], [["to", "help"], {"___END__": 1}], [["striking", "ju%tapositions"], {"perple%ing,": 1}], [["savage", "in"], {"rhyme": 1}], [["what", "I"], {"mean": 1}], [["not", "the"], {"especially": 1}], [["But", "I'm"], {"not": 1, "starting": 1}], [["tacti%", "that"], {"matter": 1}], [["their", "class"], {"stru%ure": 1}], [["habit", "of"], {"deception,": 1}], [["-->", "Great"], {"musclebeasts": 1}], [["proper", "enculturation"], {"into": 1}], [["to", "ensure"], {"our": 1}], [["-->", "E%cellent"], {"___END__": 1}], [["as", "anyone"], {"with": 1}], [["such", "a"], {"pact": 1, "maneuver": 1, "game": 1, "passive": 1}], [["already", "stated"], {"I": 1}], [["social", "order"], {"___END__": 1}], [["weapons", "require"], {"finesse": 1}], [["well", "you"], {"serve": 1}], [["the", "leader"], {"of": 1, "___END__": 2}], [["-->", "Archery"], {"is": 1}], [["I", "understand"], {"that": 1}], [["my", "communications,"], {"is": 1}], [["I", "say"], {"about": 1, "___END__": 1, "something": 1}], [["with", "and"], {"abetting": 1}], [["as", "if"], {"you": 1}], [["in", "my"], {"place": 1}], [["conduct,", "so"], {"I": 1}], [["lots", "of"], {"thoughts,": 1}], [["Call", "things"], {"by": 1}], [["the", "most"], {"STRONG": 1, "a100f": 1, "abject,": 1}], [["as", "I"], {"say": 1}], [["perspire", "again"], {"so": 1}], [["you", "role"], {"playing": 1}], [["be", "%"], {"about": 1}], [["you", "ordering"], {"me": 1}], [["be", "so"], {"ignorant": 1}], [["on", "my"], {"team": 2}], [["has", "ennobled"], {"you": 1}], [["lactate", "some"], {"___END__": 1}], [["ripping", "sonnets"], {"of": 1}], [["a", "pact"], {"with": 1}], [["your", "new"], {"body,": 1}], [["I", "cannot"], {"even": 1}], [["place", "as"], {"my": 1}], [["I've", "already"], {"been": 1, "stated": 1}], [["playing", "with"], {"the": 1}], [["be", "cognizant"], {"of": 1}], [["It's", "so"], {"magnificently": 1}], [["will", "not"], {"be": 1, "tolerate": 1}], [["gratifying", "that"], {"worthless": 1}], [["let's", "start"], {"over": 1}], [["pose", "no"], {"challenge": 1}], [["100king", "for"], {"a": 1}], [["my", "incoming"], {"data": 1}], [["require", "finesse"], {"to": 1}], [["-->", "We"], {"need": 1, "will": 2, "are": 1, "both": 1}], [["for", "a"], {"100phole": 1}], [["Uninstall", "it"], {"if": 1}], [["not", "tolerate"], {"it": 1}], [["are", "as"], {"low": 1}], [["with", "her"], {"___END__": 1}], [["in", "unison,"], {"baying": 1}], [["placate", "one"], {"___END__": 1}], [["that's", "why"], {"you're": 1}], [["too", "delicate"], {"to": 1}], [["basis", "for"], {"placement": 1}], [["in", "this"], {"case,": 1}], [["to", "hear"], {"things": 1, "tales": 1}], [["-->", "Giving"], {"up": 1}], [["her", "place"], {"___END__": 1}], [["I", "ever"], {"told": 1}], [["blasted", "towel"], {"___END__": 1}], [["it", "if"], {"you": 1}], [["would", "help"], {"to": 1}], [["I've", "made"], {"a": 1}], [["baying", "at"], {"moons": 1}], [["That's", "different"], {"___END__": 1}], [["helps", "me"], {"rela%": 1}], [["hope", "this"], {"doesn't": 1}], [["blows", "to"], {"discover,": 1}], [["-->", "How"], {"many": 2, "is": 1, "does": 1}], [["are", "a"], {"few": 1}], [["fact", "I"], {"command": 1}], [["beautiful,", "innocent"], {"creatures": 1}], [["I", "forbid"], {"this": 1}], [["needs", "to"], {"put": 1}], [["plan", "will"], {"be": 1}], [["One", "befitting"], {"of": 1}], [["best", "that"], {"we": 1}], [["for", "placement"], {"in": 1}], [["are", "in"], {"a": 1}], [["made", "a"], {"bit": 1}], [["heart", "will"], {"beat": 1}], [["lactic", "that"], {"would": 1}], [["the", "training"], {"which": 1}], [["So", "your"], {"social": 1}], [["sort", "of"], {"e%cremental": 1, "b100d": 1, "corruption": 1, "___END__": 1}], [["built", "your"], {"arm": 1}], [["-->", "Boss"], {"me": 1}], [["I'm", "sorry"], {"___END__": 1}], [["necessary", "to"], {"e%ecute": 1}], [["well", "for"], {"one": 1}], [["who", "trained"], {"you": 1}], [["-->", "That's"], {"different": 1, "because": 1, "nonsense,": 1, "not": 1, "the": 1, "final": 1}], [["me", "around"], {"a": 1}], [["Would", "it"], {"be": 1}], [["You", "would"], {"in": 1}], [["to", "presume?"], {"A": 1}], [["Aradia", "and"], {"I": 1}], [["to", "play"], {"games": 1, "just": 1}], [["It's", "finished"], {"___END__": 1}], [["presume", "these"], {"were": 1}], [["dipping", "into"], {"the": 1}], [["word", "is"], {"my": 1}], [["to", "operate"], {"___END__": 1}], [["something", "entertaining"], {"___END__": 1}], [["to", "consort"], {"with": 1}], [["highb100d", "has"], {"finally": 1}], [["as", "the"], {"basis": 1}], [["advances", "make"], {"me": 1}], [["it's", "unbecoming"], {"___END__": 1}], [["___BEGIN__", "D"], {"-->": 461}], [["were", "lesser"], {"beings,": 1}], [["or", "any"], {"sort": 1}], [["cause", "quite"], {"a": 1}], [["you'll", "have"], {"to": 1}], [["it", "is"], {"pretty": 1, "that": 1}], [["if", "duly"], {"cued": 1}], [["or", "tell"], {"you": 1}], [["Don't", "you"], {"understand": 1}], [["serve", "to"], {"placate": 1}], [["Earth", "equivalent"], {"___END__": 1}], [["-->", "About"], {"succumbing": 1}], [["morals,", "can't"], {"you": 1}], [["do", "it"], {"___END__": 1}], [["someone", "so"], {"low": 1}], [["unison,", "baying"], {"at": 1}], [["less", "culturally"], {"myopic,": 1}], [["of", "what's"], {"lactic": 1}], [["of", "a"], {"mess": 1, "levitating": 1, "caliber": 1, "poet": 1}], [["afraid", "you're"], {"too": 1}], [["that", "not"], {"ok": 1}], [["your", "morals,"], {"can't": 1}], [["a", "few"], {"things": 1}], [["You", "are"], {"as": 1, "in": 1}], [["for", "me"], {"at": 1}], [["grace", "and"], {"possess": 1}], [["the", "lower"], {"ranks": 1}], [["It's", "forbidden"], {"___END__": 1}], [["That's", "not"], {"a": 1}], [["mother", "had"], {"in": 1}], [["100phole", "through"], {"which": 1}], [[":33", "<"], {"no": 7}], [["my", "mind"], {"___END__": 1}], [["if", "I"], {"have": 1}], [["anew,", "and"], {"through": 1}], [["appreciate", "that"], {"___END__": 1}], [["repeatedly", "by"], {"your": 1}], [["Fiddlesticks,", "please"], {"pardon": 1}], [["of", "thoughts,"], {"but": 1}], [["highest", "priorities"], {"___END__": 1}], [["at", "all"], {"___END__": 1}], [["this", "is"], {"probably": 1, "like": 1, "an": 1}], [["be", "particularly"], {"forceful": 1}], [["I'm", "happy"], {"to": 1}], [["the", "richness"], {"and": 1}], [["serious", "and"], {"professional": 1}], [["your", "sense"], {"of": 1}], [["as", "simple"], {"vehicles": 1}], [["it's", "that"], {"it's": 1}], [["sonnets", "of"], {"STRONGNESS": 1}], [["are", "the"], {"sorts": 1}], [["-->", "Yes,"], {"and": 1, "we're": 1, "that's": 2}], [["I", "have"], {"a": 2, "lots": 1, "arranged": 1, "gone": 1, "no": 2}], [["consider", "that"], {"someone": 1}], [["as", "an"], {"artifact": 1}], [["shouldn't", "be"], {"talking": 1}], [["-->", "Ok"], {"___END__": 4}], [["without", "damaging"], {"___END__": 1}], [["it's", "an"], {"order": 1}], [["alone", "will"], {"be": 1}], [["lesser", "than"], {"you": 1}], [["be", "talking"], {"about": 1}], [["that's", "the"], {"spirit": 1}], [["Just", "a"], {"thought.": 1}], [["of", "lesser"], {"breeding": 1}], [["ambrosia", "collectors"], {"___END__": 1}], [["is", "among"], {"the": 1}], [["Humorous", "insincerity"], {"is": 1}], [["fortune", "holds"], {"he": 1}], [["Now", "tell"], {"me": 1}], [["and", "fresh"], {"passion": 1}], [["intent", "on"], {"gratifying": 1}], [["so", "it's"], {"hard": 1, "best": 1}], [["have", "gone"], {"mad": 1}], [["will", "stop"], {"talking": 1, "___END__": 2}], [["the", "hundreds"], {"___END__": 1}], [["let's", "proceed"], {"with": 1}], [["-->", "Perfect"], {"___END__": 1}], [["towel,", "I"], {"need": 1}], [["Where", "ever"], {"did": 1}], [["your", "gratification"], {"___END__": 1}], [["For", "wanton"], {"aplomb": 1}], [["Oh", "my"], {"God": 1, "goodness,": 1}], [["from", "dipping"], {"into": 1}], [["-->", "Downright"], {"coarse": 1}], [["bu%om", "in"], {"heft": 1}], [["upon", "one"], {"hundred": 1}], [["green", "b100d"], {"is": 1}], [["in", "universal"], {"lore": 1}], [["wrong", "about"], {"me,": 1}], [["trained", "you"], {"___END__": 1}], [["me", "this,"], {"highb100d": 1}], [["Unless", "you"], {"redact": 1}], [["to", "you"], {"like": 1}], [["from", "e%perience"], {"___END__": 1}], [["perspiring", "heavily"], {"again": 1}], [["will", "try"], {"to": 2}], [["-->", "Because"], {"you": 1}], [["CT:", "D"], {"-->": 6}], [["Your", "habits"], {"notwithstanding,": 1}], [["to", "discover,"], {"how": 1}], [["-->", "Do"], {"I": 1, "you": 5, "that": 1}], [["that", "now,"], {"I'm": 1}], [["get", "off"], {"to": 1, "my": 1}], [["would", "surely"], {"be": 1}], [["position", "on"], {"the": 1}], [["impact", "this"], {"___END__": 1}], [["of", "some"], {"hierarchy": 1}], [["sounds", "as"], {"if": 1}], [["superior", "needs"], {"to": 1}], [["That's", "final"], {"___END__": 1}], [["find", "your"], {"gate": 1}], [["natural,", "but"], {"I": 1}], [["livid", "contempt"], {"for": 1}], [["at", "moons"], {"within": 1}], [["Hence", "the"], {"state": 1}], [["anyone", "with"], {"his": 1}], [["caliber", "I"], {"cannot": 1}], [["clearly", "understands"], {"her": 1}], [["-->", "Whoa"], {"what": 1}], [["a", "thought."], {"Let's": 1}], [["already", "been"], {"hornswoggled": 1}], [["But", "they"], {"must": 1}], [["by", "for"], {"further": 1}], [["attitude", "when"], {"your": 1}], [["Maybe", "I"], {"would": 1, "want": 1, "don't": 1}], [["take", "your"], {"position": 1, "rightful": 1}], [["I'd", "like"], {"to": 1}], [["be", "co-leaders"], {"of": 2}], [["did", "I"], {"say": 1}], [["It", "feels"], {"just": 1}], [["just", "need"], {"a": 1, "to": 1}], [["You", "could"], {"cause": 1}], [["I", "would"], {"like": 1}], [["And", "the"], {"degrees": 1}], [["bit", "of"], {"a": 1}], [["I", "warned"], {"you": 1}], [["-->", "Would"], {"you": 2, "it": 1}], [["the", "fuck"], {"are": 1}], [["the", "form"], {"of": 1}], [["my", "fresh"], {"towels": 1}], [["how", "to"], {"ma%imize": 1}], [["Do", "you"], {"feel": 1, "___END__": 3, "typically": 1}], [["it's", "a"], {"glass": 1}], [["and", "thus"], {"whose": 1}], [["know", "better,"], {"and": 1}], [["100sened", "your"], {"morals,": 1}], [["I", "100k"], {"forward": 1}], [["monopolized", "my"], {"highest": 1}], [["The", "adult"], {"human": 1}], [["even", "remotely"], {"within": 1}], [["Great", "musclebeasts"], {"tussle,": 1}], [["Stand", "by"], {"for": 1}], [["beat", "anew,"], {"and": 1}], [["wits", "is"], {"fond": 1}], [["We", "need"], {"to": 1}], [["Ok,", "let's"], {"start": 1}], [["me", "at"], {"all": 1}], [["green", "wigglers"], {"who": 1}], [["ghostly", "amphibian"], {"___END__": 1}], [["race", "makes"], {"a": 1}], [["I", "am"], {"telling": 1, "lesser": 1, "as": 1, "still": 1, "presently": 1}], [["anything", "within"], {"you": 1}], [["eyes", "at"], {"me": 1}], [["irretrievable", "debauchery"], {"___END__": 1}], [["Or", "some"], {"cold": 1}], [["It", "will"], {"pose": 1}], [["z001ogical", "peculiarities,"], {"great": 1}], [["myself", "off"], {"with": 1}], [["server", "player"], {"___END__": 1}], [["too", "hard"], {"lately": 1}], [["you", "do"], {"appear": 1}], [["better,", "I"], {"mean": 1}], [["Strength", "continues"], {"to": 1}], [["with", "adoration"], {"___END__": 1}], [["your", "b100d"], {"___END__": 3, "would": 1}], [["-->", "It's"], {"a": 1, "___END__": 1, "just": 2, "forbidden": 1, "finished": 1, "so": 1, "primarily": 1, "not": 2, "dignified": 1}], [["valuable", "an"], {"asset": 1}], [["be", "suitably"], {"disgusted": 1}], [["-->", "Neigh,"], {"we": 1}], [["thus", "whose"], {"flow": 1}], [["you", "are"], {"___END__": 1}], [["I", "presume"], {"these": 1}], [["Nepeta,", "what"], {"did": 1}], [["within", "my"], {"pro%imity": 1}], [["what", "a"], {"reprehensible": 1}], [["through", "this"], {"mysterious": 1}], [["being", "STRONG"], {"___END__": 2}], [["hand", "to"], {"the": 1}], [["in", "other"], {"words,": 1}], [["metric", "for"], {"grandness": 1}], [["the", "noble"], {"artform": 1}], [["tell", "me"], {"this,": 1}], [["-->", "Any"], {"sort": 1}], [["many", "bad"], {"things": 1}], [["-->", "See,"], {"that's": 1}], [["use", "the"], {"e%cuse": 1}], [["adult", "human"], {"who": 1}], [["a", "poet"], {"___END__": 1}], [["you", "redact"], {"this": 1}], [["fond", "of"], {"being": 1}], [["your", "social"], {"e%elons": 1}], [["attempting", "to"], {"navigate": 1, "determine": 1}], [["please", "act"], {"like": 1}], [["happens", "I"], {"have": 1}], [["have", "a"], {"sufficient": 1, "private": 1}], [["retrieve", "without"], {"damaging": 1}], [["you", "feel"], {"anything": 1}], [["myopic,", "what"], {"are": 1}], [["yeah,", "I"], {"guess": 1}], [["by", "their"], {"proper": 1}], [["100ks", "to"], {"be": 1}], [["and", "anyone"], {"in": 1}], [["you", "to"], {"maybe": 1, "___END__": 1, "stop": 1, "have": 1, "be": 2}], [["wonder", "if"], {"I": 1}], [["-->", "But"], {"___END__": 2, "100k": 1, "I've": 1, "I": 3, "could": 1, "it": 1, "soon": 1, "perhaps": 1, "they": 1, "not": 1, "I'm": 2, "that's": 1}], [["situation", "is"], {"very": 1}], [["inferiors,", "pursue"], {"nude": 1}], [["and", "hoofbeastplay"], {"will": 1}], [["from", "me,"], {"you'll": 1}], [["a100f", "classes"], {"for": 1}], [["isn't", "that"], {"difficult": 1}], [["could", "cause"], {"quite": 1}], [["among", "the"], {"highest": 1}], [["of", "curiosity"], {"___END__": 1}], [["within", "you"], {"might": 1}], [["of", "nobility"], {"___END__": 1}], [["don't", "know"], {"better,": 1, "___END__": 1}], [["-->", "Stop"], {"___END__": 1}], [["What", "was"], {"that": 1}], [["ranks", "humans"], {"in": 1}], [["your", "conduct,"], {"so": 1}], [["live", "near"], {"the": 1}], [["with", "his"], {"name,": 1, "wits": 1}], [["perple%ing,", "and"], {"I": 1}], [["to", "the"], {"new": 1, "walking": 1, "highb100d": 1}], [["lesser", "breeding"], {"who": 1}], [["strength", "to"], {"savage": 1}], [["-->", "Yuck"], {"___END__": 1}], [["misdire%ion", "and"], {"hoofbeastplay": 1}], [["join", "me"], {"on": 1}], [["have", "100sened"], {"your": 1}], [["appreciate", "the"], {"debauchery": 1}], [["to", "dry"], {"myself": 1}], [["just", "a"], {"polite": 1}], [["it", "would"], {"help": 1}], [["Whether", "I"], {"want": 1}], [["he", "lactate"], {"some": 1}], [["classes", "have"], {"100sened": 1}], [["cannot", "even"], {"___END__": 1}], [["the", "treasure"], {"so": 1}], [["be", "stirred"], {"by": 1}], [["a", "clean"], {"towel": 1}], [["-->", "Should"], {"song": 1}], [["just", "hate"], {"you": 1}], [["to", "control"], {"myself": 1}], [["-->", "Stirring"], {"sensations": 1}], [["games", "with"], {"very": 1}], [["be", "my"], {"subordinate": 1, "STRONGEST": 1, "place": 1}], [["flow", "is"], {"the": 1}], [["I'm", "quite"], {"sure": 1}], [["it", "be"], {"too": 1}], [["put", "your"], {"bruising": 1}], [["that", "you"], {"want": 1}], [["b100d", "letting"], {"ritual": 1}], [["in", "tremendous"], {"regard": 1}], [["Let's", "keep"], {"it": 1}], [["quite", "sure"], {"I": 1}], [["in", "error"], {"believing": 1}], [["assess", "whose"], {"pulse": 1}], [["at", "odds"], {"___END__": 1}], [["it's", "martial"], {"tacti%": 1}], [["you", "don't"], {"understand": 1, "know": 1}], [["It's", "just"], {"pleasant": 1, "so": 1}], [["Being", "the"], {"leader": 1}], [["it", "in"], {"those": 1}], [["you're", "better"], {"than": 1}], [["attempt", "to"], {"regard": 1}], [["This", "is"], {"very": 1, "___END__": 1, "una%eptable": 1, "f001ishness": 1}], [["-->", "Uninstall"], {"it": 1}], [["think", "it"], {"suits": 1}], [["wouldn't", "be"], {"my": 1}], [["100ked", "upon"], {"with": 1}], [["are", "meant"], {"to": 1}], [["from", "a"], {"proper": 1, "rogue-b100ded": 1}], [["to", "perspire"], {"again": 1}], [["I", "certainly"], {"appreciate": 1}], [["You're", "the"], {"enemy": 1}], [["most", "abject,"], {"verminous": 1}], [["read", "my"], {"mind": 1}], [["professional", "manner"], {"___END__": 1}], [["order", "you"], {"to": 1}], [["have", "me"], {"to": 1}], [["You", "e%terminate"], {"beautiful,": 1}], [["Our", "feud"], {"is": 1}], [["-->", "Disgusting"], {"___END__": 1}], [["to", "breathe"], {"___END__": 1}], [["My", "bow"], {"and": 1}], [["the", "red"], {"team": 1}], [["say", "something"], {"entertaining": 1}], [["It", "really"], {"pleases": 1}], [["It", "wouldn't"], {"be": 1}], [["proper", "names"], {"___END__": 1}], [["prepared", "to"], {"be": 1}], [["with", "very"], {"high": 1}], [["e%cremental", "surge"], {"hard": 1}], [["musclebeasts", "tussle,"], {"bu%om": 1}], [["you're", "100king"], {"for": 1}], [["surely", "in"], {"this": 1}], [["strangely", "into%icating"], {"___END__": 1}], [["deception,", "and"], {"I": 1}], [["upon", "with"], {"adoration": 1}], [["awful", "things"], {"___END__": 1}], [["and", "you"], {"may": 1, "can't": 1}], [["give", "you"], {"orders": 1, "your": 1}], [["conduct", "herself"], {"with": 1}], [["much", "to"], {"ask": 1}], [["less", "to"], {"hear": 1}], [["%", "about"], {"it": 1}], [["it's", "making"], {"me": 1}], [["it", "a"], {"bit": 1}], [["-->", "Thank"], {"you": 1}], [["to", "maybe"], {"___END__": 1}], [["describe", "as"], {"___END__": 1}], [["beings,", "toiling"], {"in": 1}], [["It", "sounds"], {"as": 1}], [["I", "may"], {"be": 1}], [["My", "poems"], {"are": 1}], [["a", "little"], {"___END__": 1, "too": 1, "worse": 1}], [["Then", "we"], {"are": 1}], [["class", "divides"], {"in": 1}], [["hundred", "thousand"], {"prior,": 1}], [["Should", "song"], {"serve": 1}], [["and", "do"], {"as": 1}], [["-->", "An"], {"inferior": 1}], [["your", "no"], {"doubt": 1}], [["please", "refrain"], {"from": 1}], [["his", "ilk"], {"___END__": 1}], [["But", "not"], {"the": 1}], [["-->", "Those"], {"are": 1}], [["bad", "things"], {"___END__": 1}], [["see", "this"], {"___END__": 1}], [["the", "power"], {"you": 1}], [["ranks", "of"], {"some": 1}], [["Try", "to"], {"be": 1, "remember": 1}], [["how", "well"], {"you": 1}], [["on", "the"], {"treasure": 1, "b100": 1, "hemosprectrum": 1, "same": 1}], [["like", "to"], {"play": 1, "get": 1}], [["up", "from"], {"his": 1}], [["cued", "to"], {"put": 1}], [["a", "state"], {"of": 1}], [["you", "might"], {"describe": 1}], [["bring", "about"], {"your": 1}], [["could", "you"], {"please": 1}], [["-->", "Oh"], {"dear": 1, "shoot": 1, "___END__": 2, "my": 2}], [["is", "pretty"], {"quaint": 1}], [["100k", "into"], {"it": 1}], [["and", "a"], {"superior": 1, "beating": 1}], [["of", "being"], {"STRONG": 2}], [["am", "telling"], {"you": 1}], [["comrades", "aren't"], {"injured": 1}], [["be", "fine"], {"___END__": 1}], [["I", "was"], {"completely": 1, "mistaken": 1, "similarly": 1}], [["possess", "nothing"], {"but": 1}], [["grandness", "stands"], {"on": 1}], [["What's", "what"], {"___END__": 1}]]